Workbook
Name \Z: #REF!
Name \Z: #REF!
Name __?: #REF!
Name __??????: #REF!
Name ___?: #REF!
Name ___??????: #REF!
Name ____?: #REF!
Name ____??????: #REF!
Name ____cao1: #REF!
Name ____cao2: #REF!
Name ____cao3: #REF!
Name ____cao4: #REF!
Name ____cao5: #REF!
Name ____cao6: #REF!
Name ____dai1: #REF!
Name ____dai2: #REF!
Name ____dai3: #REF!
Name ____dai4: #REF!
Name ____dai5: #REF!
Name ____dai6: #REF!
Name ____dan1: #REF!
Name ____dan2: #REF!
Name ____ddn400: #REF!
Name ____ddn600: #REF!
Name ____lap1: #REF!
Name ____lap2: #REF!
Name ____MAC12: #REF!
Name ____MAC46: #REF!
Name ____NCL100: #REF!
Name ____NCL200: #REF!
Name ____NCL250: #REF!
Name ____nin190: #REF!
Name ____phi10: #REF!
Name ____phi12: #REF!
Name ____phi14: #REF!
Name ____phi16: #REF!
Name ____phi18: #REF!
Name ____phi20: #REF!
Name ____phi22: #REF!
Name ____phi25: #REF!
Name ____phi28: #REF!
Name ____phi6: #REF!
Name ____phi8: #REF!
Name ____SN3: #REF!
Name ____TB1: #REF!
Name ____TL1: #REF!
Name ____TL2: #REF!
Name ____TL3: #REF!
Name ____TLA120: #REF!
Name ____TLA35: #REF!
Name ____TLA50: #REF!
Name ____TLA70: #REF!
Name ____TLA95: #REF!
Name ____VL100: #REF!
Name ____VL200: #REF!
Name ____VL250: #REF!
Name ___cao1: #REF!
Name ___cao2: #REF!
Name ___cao3: #REF!
Name ___cao4: #REF!

Sheet KQHDKD
A1: =CDPS!A1 -> 公司名/Tên CSKD: CÔNG TY TNHH NGẠN CHÂU
A2: =CDPS!A2 -> 地址/Địa Chỉ : 30KL, Tổ 1, Khu phố Khánh Long, Phường Tân Khánh, TP Hồ Chí Minh, Việt Nam
A3: =CDPS!A3 -> 税号/Mã số thuế: 3702307012
A5: BÁO CÁO KẾT QUẢ HOẠT ĐỘNG SẢN XUẤT KINH DOANH 损益表
A6: (Ban hành theo Thông tư số 200/2014/TT-BTC Ngày 22/12/2014 của Bộ BTC)
A7: =CDKT!A6 -> (Từ 01/01/2025 Đến 31/01/2025)
F8: Đơn vị tiền: VNĐ
A9: STT | B9: Tên chỉ tiêu 摘要名稱 | C9: Tên chỉ tiêu tiếng Hoa 中文摘要名稱 | D9: Mã | E9: Thuyết minh | F9: NĂM 2025年 | G9: NĂM 2024年
A10: -1 | B10: -2 | C10: -3 | D10: -4 | E10: -5 | F10: -6 | G10: -7
A11: 1 | B11: Doanh thu bán hàng và cung cấp dịch vụ | C11: 1. 銷貨及提供勞務營收 | D11: 01 | E11: 18. | F11: 5951365361 | G11: 8087186237
A12: 2 | B12: Các khoản giảm trừ doanh thu | C12: 2. 各項扣減帳款 | D12: 02
A13: 3 | B13: Doanh thu thuần về bán hàng và cung cấp dịch vụ (10 = 01 - 02) | C13: 3. 銷貨及提供勞務淨額 (10 = 01 - 02) | D13: 10 | F13: 5951365361 | G13: 8087186237
A14: 4 | B14: Giá vốn hàng bán | C14: 4. 銷貨成本 | D14: 11 | E14: 19. | F14: 5913632751 | G14: 7712329356
A15: 5 | B15: Lợi nhuận gộp về bán hàng và cung cấp dịch vụ (20 = 10 - 11) | C15: 5. 銷貨及提供勞務毛利 (20 = 10 - 11) | D15: 20 | F15: 37732610 | G15: 374856881
A16: 6 | B16: Doanh thu hoạt động tài chính | C16: 6. 非營業收益 | D16: 21 | E16: 20. | F16: 2779695 | G16: 3893447
A17: 7 | B17: Chi phí tài chính | C17: 7. 非營業費用 | D17: 22 | E17: 21. | F17: 31932647 | G17: 383058272
B18: - Trong đó: Chi phí lãi vay | C18: - 其中：利息費用 | D18: 23 | F18: 0 | G18: 161194679
A19: 8 | B19: Chi phí bán hàng | C19: 8. 銷貨費用 | D19: 25 | E19: 22. | F19: 33711035 | G19: 48211218
A20: 9 | B20: Chi phí quản lý doanh nghiệp | C20: 9. 營業管理費用 | D20: 26 | E20: 23. | F20: 1.270792e+09 | G20: 1609567641
A21: 10 | B21: Lợi nhuận thuần từ hoạt động kinh doanh (30 = 20 + (21 - 22) - (24 + 25)) | C21: 10. 營業利潤[30=20+(21-22)-(24+25)] | D21: 30 | F21: -1.2959234e+09 | G21: -1662086803
A22: 11 | B22: Thu nhập khác | C22: 11. 其他收益 | D22: 31 | E22: 24. | F22: 1451751 | G22: 47604542
A23: 12 | B23: Chi phí khác | C23: 12. 其他費用 | D23: 32 | E23: 25. | F23: 1605130403 | G23: 27676
A24: 13 | B24: Lợi nhuận khác (40 = 31 - 32) | C24: 13. 其他利潤 (40 = 31 - 32) | D24: 40 | F24: -1603678652 | G24: 47576866
A25: 14 | B25: Tổng lợi nhuận kế toán trước thuế (50 = 30 + 40) | C25: 14. 稅前總利潤(50 = 30 + 40) | D25: 50 | F25: -2.899602e+09 | G25: -1614509937
A26: 15 | B26: Chi phí thuế thu nhập doanh nghiệp hiện hành | C26: 15. 現行企業營所稅費用 | D26: 51 | E26: 26.
A27: 16 | B27: Chi phí thuế thu nhập doanh nghiệp hoãn lại | C27: 16. 遞延企業營所稅費用 | D27: 52
A28: 17 | B28: Lợi nhuận sau thuế thu nhập doanh nghiệp (60 = 50 - 51 - 52) | C28: 17. 稅後利潤 (60=50-51-52) | D28: 60 | F28: -2.899602e+09 | G28: -1614509937
A29: 18 | B29: Lãi cơ bản trên cổ phiếu (*) | D29: 70
A30: 19 | B30: Lãi suy giảm trên cổ phiếu (*) | D30: 71
D32: BD, ngày 31 tháng 01 năm 2025
A33: Người lập biểu | E33: Giám Đốc
E37: HSIEH, YAO-YI

Sheet CDKT
A1: =CDPS!A1 -> 公司名/Tên CSKD: CÔNG TY TNHH NGẠN CHÂU
A2: =CDPS!A2 -> 地址/Địa Chỉ : 30KL, Tổ 1, Khu phố Khánh Long, Phường Tân Khánh, TP Hồ Chí Minh, Việt Nam
A3: =CDPS!A3 -> 税号/Mã số thuế: 3702307012
A4: BẢNG CÂN ĐỐI KẾ TOÁN -资产负债表
A5: (Ban hành theo thông tư 200/2014/TT-BTC ngày 22/12/2014 của bộ trưởng BTC)
A6: (Từ 01/01/2025 Đến 31/01/2025)
F7: Đơn vị tiền: VNĐ
A8: STT | B8: Tên chỉ tiêu 摘要名稱 | C8: Tên chỉ tiêu tiếng Hoa 中文摘要名稱 | D8: Mã số 編號 | E8: Thuyết minh 說明 | F8: NĂM 2025年 | G8: NĂM 2024年
A9: -1 | B9: -2 | C9: -3 | D9: -4 | E9: -5 | F9: -6 | G9: -7
B10: TÀI SẢN | C10: 資產
A11: A | B11: A - TÀI SẢN NGẮN HẠN (100=110+120+130+140+150) | C11: A. 短期資產(100=110+120+130+140+150) | D11: 100 | F11: 3519687206 | G11: 6956519842 | H11: x
A12: I | B12: I. Tiền và các khoản tương đương tiền (110=111+112) | C12: I. 現金及各約當現金 | D12: 110 | E12: 5. | F12: 1991633255 | G12: 2837155407 | H12: x
A13: 1 | B13: 1. Tiền | C13: 1. 現金 | D13: 111 | F13: 1991633255 | G13: 2837155407 | H13: x
A14: 2 | B14: 2. Các khoản tương đương tiền | C14: 2. 各約當現金 | D14: 112 | G14: 0
A15: II | B15: II. Các khoản đầu tư tài chính ngắn hạn (120=121+129) | C15: II. 短期金融投資 | D15: 120 | F15: 0 | G15: 0
A16: 1 | B16: 1. Chứng khoán kinh doanh | C16: 1. 證券投資 | D16: 121
A17: 2 | B17: 2. Dự phòng giảm giá đầu tư ngắn hạn | C17: 2. 短期投資跌價損失備抵 | D17: 122
A18: 3 | B18: 3. Đầu tư nắm giữ đến ngày đáo hạn | C18: 3.短期到期性投資 | D18: 123
A19: III | B19: III. Các khoản phải thu ngắn hạn (130 = 131 + 132 + 133 + 134 + 135 + 139) | C19: III. 短期應收 | D19: 130 | F19: 1443322235 | G19: 2073224734 | H19: x
A20: 1 | B20: 1. Phải thu khách hàng | C20: 1. 應收帳款 | D20: 131 | E20: 6a. | F20: 5209726965 | G20: 5839629464 | H20: x
A21: 2 | B21: 2. Trả trước cho người bán | C21: 2. 預付貨款 | D21: 132 | G21: 0 | H21: x
A22: 3 | B22: 3. Phải thu nội bộ ngắn hạn | C22: 3. 短期應收內部 | D22: 133
A23: 4 | B23: 4. Phải thu theo tiến độ HĐXD | C23: 4. 依據營造合約進度收款 | D23: 134
A24: 5 | B24: 5. Phải thu về cho vay ngắn hạn | C24: 5. 應收短期借款 | D24: 135
A25: 6 | B25: 6. Các khoản phải thu khác | C25: 6. 其他短期應收款 | D25: 136 | F25: 0 | G25: 0
A26: 7 | B26: 7. Dự phòng phải thu ngắn hạn khó đòi | C26: 7. 待處理資產 | D26: 137 | E26: 7. | F26: -3766404730 | G26: -3766404730 | H26: x
A27: 8 | B27: 8. Tài sản thiếu chờ xử lý | C27: 8. 備抵呆帳 | D27: 139
A28: IV | B28: IV. Hàng tồn kho (140 = 141 + 149) | C28: IV. 庫存 | D28: 140 | F28: 0 | G28: 1863554838 | H28: x
A29: 1 | B29: 1. Hàng tồn kho | C29: 1. 庫存貨 | D29: 141 | E29: 8. | F29: 0 | G29: 1863554838 | H29: x
A30: 2 | B30: 2. Dự phòng giảm giá hàng tồn kho | C30: 2. 庫存貨跌價損失備抵 | D30: 149 | F30: 0 | G30: 0
A31: V | B31: V. Tài sản ngắn hạn khác (150 = 151 + 152 + 153 + 154 + 155) | C31: V. 其他短期資產 | D31: 150 | F31: 84731716 | G31: 182584863 | H31: x
A32: 1 | B32: 1. Chi phí trả trước ngắn hạn | C32: 短期預付款 | D32: 151 | E32: 9a. | F32: 16727359 | G32: 114580506 | H32: x
A33: 2 | B33: 2. Thuế GTGT được khấu trừ | C33: 進項增值稅 | D33: 152 | E33: 11. | F33: 0 | G33: 0
A34: 3 | B34: 3. Thuế và các khoản khác phải thu Nhà nước | C34: 應收國家稅款及其他帳款 | D34: 153 | E34: 12. | F34: 68004357 | G34: 68004357 | H34: x
A35: 4 | B35: 4. Giao dịch mua bán lại trái phiếu Chính phủ | C35: 政府債券交易 | D35: 154
A36: 5 | B36: 5. Tài sản ngắn hạn khác | C36: 其他短期資產 | D36: 155
A37: B | B37: B - TÀI SẢN DÀI HẠN (200=210+220+240+250+260) | C37: B. 長期資產 (200=210+220+240+250+260) | D37: 200 | F37: 1180725012 | G37: 1610698456 | H37: x
A38: I | B38: I- Các khoản phải thu dài hạn (210 = 211 + 212 + 213 + 214 + 215 +216 + 219) | C38: I. 長期應收 | D38: 210 | F38: 0 | G38: 0
A39: 1 | B39: 1. Phải thu dài hạn của khách hàng | C39: 1. 長期應收 | D39: 211
A40: 2 | B40: 2. Trả trước cho người bán dài hạn | C40: 長期預付貨款 | D40: 212 | F40: 0
A41: 3 | B41: 3. Vốn kinh doanh ở đơn vị trực thuộc | C41: 2. 直屬單位的經營資金 | D41: 213
A42: 4 | B42: 4. Phải thu nội bộ dài hạn | C42: 3. 長期應收內部 | D42: 214
A43: 5 | B43: 5. Phải thu về cho vay dài hạn | C43: 應收長期借款 | D43: 215
A44: 6 | B44: 6. Phải thu dài hạn khác | C44: 4. 其他長期應收 | D44: 216
A45: 7 | B45: 7. Dự phòng phải thu dài hạn khó đòi | C45: 5. 長期應收壞帳備抵 | D45: 219
A46: II | B46: II. Tài sản cố định - (220 = 221 + 224 + 227 + 230) | C46: II. 固定資產 | D46: 220 | F46: 1174754689 | G46: 1604042485 | H46: x
A47: 1 | B47: 1. Tài sản cố định hữu hình | C47: 1. 有形固定資產 | D47: 221 | E47: 10. | F47: 1174754689 | G47: 1604042485 | H47: x
A48: - | B48: - Nguyên giá | C48: - 原價 | D48: 222 | F48: 3517239273 | G48: 3517239273 | H48: x
A49: - | B49: - Giá trị hao mòn lũy kế | C49: - 累積折舊值 | D49: 223 | F49: -2342484584 | G49: -1913196788 | H49: x
A50: 2 | B50: 2. Tài sản cố định thuê tài chính | C50: 2. 籌資性租賃資產 | D50: 224 | F50: 0 | G50: 0
A51: - | B51: - Nguyên giá | C51: - 原價 | D51: 225
A52: - | B52: - Giá trị hao mòn lũy kế | C52: - 累積折舊值 | D52: 226
A53: 3 | B53: 3. TSCĐ vô hình | C53: 3. 無形固定資產 | D53: 227 | F53: 0 | G53: 0
A54: - | B54: - Nguyên giá | C54: - 原價 | D54: 228
A55: - | B55: - Giá trị hao mòn lũy kế | C55: - 累積折舊值 | D55: 229
A56: III | B56: III. Bất động sản đầu tư (230 = 231 + 232) | C56: III. 不動產投資 | D56: 230
A57: - | B57: - Nguyên giá | C57: - 原價 | D57: 231
A58: - | B58: - Giá trị hao mòn lũy kế | C58: - 累積折舊值 | D58: 232
A59: IV | B59: IV. Tài sản dở dang dài hạn | C59: IV. 長期在建資產 | D59: 240 | F59: 0 | G59: 0
A60: 1 | B60: 1. Chi phí sản xuất, kinh doanh dở dang dài hạn | C60: 長期生產經營費用 | D60: 241
A61: 2 | B61: 2. Chi phí xây dựng cơ bản dở dang | C61: 長期在建工程 | D61: 242
A62: V | B62: V. Đầu tư tài chính dài hạn (250 = 251 + 252 + 253 + 254 + 255) | C62: V. 長期金融投資 | D62: 250 | F62: 0 | G62: 0
A63: 1 | B63: 1. Đầu tư vào công ty con | C63: 1. 投資入子公司 | D63: 251
A64: 2 | B64: 2. Đầu tư vào công ty liên kết, liên doanh | C64: 2. 投資入合夥及聯營公司 | D64: 252
A65: 3 | B65: 3. Đầu tư góp vốn vào đơn vị khác | C65: 3. 其他長期投資 | D65: 253
A66: 4 | B66: 4. Dự phòng giảm giá đầu tư tài chính dài hạn | C66: 4. 長期金融投資跌價損失備抵 | D66: 254
A67: 5 | B67: 5. Đầu tư nắm giữ đến ngày đáo hạn | C67: 5.長期到期性投資 | D67: 255
A68: VI | B68: VI. Tài sản dài hạn khác (260 = 261 + 262 + 263 + 268) | C68: VI. 其他長期資產 | D68: 260 | F68: 5970323 | G68: 6655971 | H68: x
A69: 1 | B69: 1. Chi phí trả trước dài hạn | C69: 1. 長期預付費用 | D69: 261 | E69: 9b. | F69: 5970323 | G69: 6655971 | H69: x
A70: 2 | B70: 2. Tài sản thuế thu nhập hoãn lại | C70: 2. 遞延所得稅資產 | D70: 262
A71: 3 | B71: 3. Thiết bị, vật tư, phụ tùng thay thế dài hạn | D71: 263
A72: 4 | B72: 4. Tài sản dài hạn khác | C72: 4. 其他長期資產 | D72: 268
A73: TỔNG CỘNG TÀI SẢN (270 = 100 + 200) | C73: 資產總值 (270 = 100+200) | D73: 270 | F73: 4700412218 | G73: 8567218298 | H73: x
B74: NGUỒN VỐN | C74: 業主權益及負債 | H74: x
A75: A | B75: A - NỢ PHẢI TRẢ (300 = 310 + 330) | C75: A. 負債(300 = 310 + 330) | D75: 300 | F75: 11046388282 | G75: 12013592344 | H75: x
A76: I | B76: I. Nợ ngắn hạn (310 = 311 + 312 + ... + 319 + 320 + 324) | C76: I. 短期負債 | D76: 310 | F76: 11046388282 | G76: 11494734545 | H76: x
A77: 1 | B77: 1. Phải trả người bán ngắn hạn | C77: 1. 應付供應商 | D77: 311 | E77: 11. | F77: 7780782410 | G77: 8096616642 | H77: x
A78: 2 | B78: 2. Người mua trả tiền trước ngắn hạn | C78: 2.預收貨款 | D78: 312 | F78: 0 | G78: 0
A79: 3 | B79: 3. Thuế và các khoản phải nộp Nhà nước | C79: 3. 應繳國家預算之稅款與其他帳款 | D79: 313 | E79: 12. | F79: 23229829 | G79: 26345886 | H79: x
A80: 4 | B80: 4. Phải trả người lao động | C80: 4. 應付員工 | D80: 314 | E80: 13. | F80: 0 | G80: 190616509 | H80: x
A81: 5 | B81: 5. Chi phí phải trả ngắn hạn | C81: 5. 應付費用 | D81: 315
A82: 6 | B82: 6. Phải trả nội bộ ngắn hạn | C82: 6. 應付內部 | D82: 316
A83: 7 | B83: 7. Phải trả theo tiến độ kế hoạch HĐXD | C83: 7. 應付依據營造合約進度 | D83: 317
A84: 8 | B84: 8. Doanh thu chưa thực hiện ngắn hạn | C84: 8. 未實現營收 | D84: 318
A85: 9 | B85: 9. Phải trả ngắn hạn khác | C85: 9. 其他短期負債 | D85: 319 | E85: 14a. | F85: 2800000000 | G85: 2800000000 | H85: x
A86: 10 | B86: 10. Vay và nợ thuê tài chính ngắn hạn | C86: 10. 短期借款及融資租賃負債 | D86: 320 | E86: 15a. | F86: 442376043 | G86: 381155508 | H86: x
A87: 11 | B87: 11. Dự phòng phải trả ngắn hạn | C87: 11. 短期應付備抵 | D87: 321
A88: 12 | B88: 12. Quỹ khen thưởng, phúc lợi | C88: 12. 獎勵及福利基金 | D88: 322
A89: 13 | B89: 13. Quỹ bình ổn giá | C89: 13. 價格穩定基金 | D89: 323
A90: 14 | B90: 14. Giao dịch mua bán lại trái phiếu Chính phủ | C90: 14. 政府債券出售及回購交易 | D90: 324
A91: II | B91: II. Nợ dài hạn (330 = 331 + 332 + ... + 342 + 343) | C91: II. 長期負債 | D91: 330 | F91: 0 | G91: 518857799 | H91: x
A92: 1 | B92: 1. Phải trả người bán dài hạn | C92: 1. 長期應付供應商 | D92: 331
A93: 2 | B93: 2. Người mua trả tiền trước dài hạn | C93: 2. 長期預收貨款 | D93: 332
A94: 3 | B94: 3. Chi phí phải trả dài hạn | C94: 3. 長期預提費用 | D94: 333
A95: 4 | B95: 4. Phải trả nội bộ về vốn kinh doanh | C95: 4. 應付內部營運資金 | D95: 334
A96: 5 | B96: 5. Phải trả nội bộ dài hạn | C96: 5. 長期應付內部 | D96: 335
A97: 6 | B97: 6. Doanh thu chưa thực hiện dài hạn | C97: 6. 未實現營收 | D97: 336
A98: 7 | B98: 7. Phải trả dài hạn khác | C98: 7. 其他長期應付 | D98: 337
A99: 8 | B99: 8. Vay và nợ thuê tài chính dài hạn | C99: 8. 長期借款及融資租賃負債 | D99: 338 | E99: 15b. | G99: 518857799 | H99: x
A100: 9 | B100: 9. Trái phiếu chuyển đổi | C100: 9. 可轉換債券 | D100: 339
...

Sheet CDPS
A1: 公司名/Tên CSKD: CÔNG TY TNHH NGẠN CHÂU
A2: 地址/Địa Chỉ : 30KL, Tổ 1, Khu phố Khánh Long, Phường Tân Khánh, TP Hồ Chí Minh, Việt Nam
A3: 税号/Mã số thuế: 3702307012
A4: BẢNG CÂN ĐỐI TÀI KHOẢN 试算表
A5: =#REF! -> #REF!
A7: MÃ TK | B7: Tên tài khoản tiếng Hoa 中文账户名 | C7: TÊN TÀI KHOẢN | D7: Số dư đầu kỳ 期初值 | H7: Số phát sinh trong kỳ 本期發生 | L7: Số dư cuối kỳ 期末值
D8: Nợ VND 借方 | E8: Nợ USD 借方 | F8: Có VND 貸方 | G8: Có USD 貸方 | H8: Nợ VND 借方 | I8: Nợ USD 借方 | J8: Có VND 貸方 | K8: Có USD 貸方 | L8: Nợ VND 借方 | M8: Nợ USD 借方 | N8: Có VND 貸方 | O8: Có USD 貸方
A9: 1111 | B9: 現金 越盾 | C9: Tiền Việt Nam | D9: 592112098 | E9: 0 | F9: 0 | G9: 0 | H9: 1950000000 | I9: 0 | J9: 2226593842 | K9: 0 | L9: 315518256 | M9: 0 | N9: 0 | O9: 0
A10: 112704 | B10: 1121AGR | C10: Tiền gửi NH Agribank - VND 5500201022704 | D10: 165054122 | E10: 0 | F10: 0 | G10: 0 | H10: 259100 | I10: 0 | J10: 79001551 | K10: 0 | L10: 86311671 | M10: 0 | N10: 0 | O10: 0
A11: 112551 | B11: 1121IVB | C11: Tiền gửi NH IVB -VND 5044255-001 | D11: 1973206995 | E11: 0 | F11: 0 | G11: 0 | H11: 7657854800 | I11: 0 | J11: 8148040659 | K11: 0 | L11: 1483021136 | M11: 0 | N11: 0 | O11: 0
A12: 112552 | B12: 1122IVB002 | C12: Tiền gửi NH IVB - USD 5044255-002 | D12: 106759928 | E12: 4219.76 | F12: 0 | G12: 0 | H12: 0 | I12: 0 | J12: 0 | K12: 0 | L12: 106759928 | M12: 4219.76 | N12: 0 | O12: 0
A13: 112553 | B13: 1122IVB003 | C13: Tiền gửi NH IVB - USD 5044255-003 | D13: 22264 | E13: 0.88 | F13: 0 | G13: 0 | H13: 0 | I13: 0 | J13: 0 | K13: 0 | L13: 22264 | M13: 0.88 | N13: 0 | O13: 0
A14: 131ARTCRE | C14: CTY TNHH INTERNATIONAL ART CREATION | H14: 4064029 | I14: 0 | J14: 4064029 | K14: 0 | L14: 0 | M14: 0 | N14: 0 | O14: 0
A15: 131KIET | C15: CTY CP CHẤN KIỆT | D15: 13771296 | E15: 0 | F15: 0 | G15: 0 | H15: 21054298 | I15: 0 | J15: 34825594 | K15: 0 | L15: 0 | M15: 0 | N15: 0 | O15: 0
A16: 131THINH | C16: CTY TNHH CƯỜNG THỊNH | H16: 0 | I16: 0 | J16: 0 | K16: 0 | L16: 0 | M16: 0 | N16: 0 | O16: 0
A17: 131ICH | C17: CTY TNHH ĐỒ GỖ DANH ÍCH | D17: 168245139 | E17: 0 | F17: 0 | G17: 0 | H17: 651138736 | I17: 0 | J17: 789534348 | K17: 0 | L17: 29849527 | M17: 0 | N17: 0 | O17: 0
A18: 131DG | C18: CTY TNHH ĐỒ GỖ GIA DỤNG DINH GIA VN | H18: 2063880 | I18: 0 | J18: 2063880 | K18: 0 | L18: 0 | M18: 0 | N18: 0 | O18: 0
A19: 131GCKL | C19: CTY TNHH MTV GỖ GIA CÔNG KIM LỰC | D19: 170003075 | E19: 0 | F19: 0 | G19: 0 | H19: 1385120071 | I19: 0 | J19: 1309186209 | K19: 0 | L19: 245936937 | M19: 0 | N19: 0 | O19: 0
A20: 131NGHIA | C20: CTY TNHH GỖ HẰNG NGHĨA | D20: 49429129 | E20: 0 | F20: 0 | G20: 0 | H20: 250697108 | I20: 0 | J20: 300126237 | K20: 0 | L20: 0 | M20: 0 | N20: 0 | O20: 0
A21: 131HOME | C21: CTY TNHH ESLITE HOME | D21: 139968607 | E21: 0 | F21: 0 | G21: 0 | H21: 0 | I21: 0 | J21: 29976000 | K21: 0 | L21: 109992607 | M21: 0 | N21: 0 | O21: 0
A22: 131HSINYA | C22: CTY TNHH CÔNG NGHIỆP GỖ HSIN YA | D22: 1531238 | E22: 0 | F22: 0 | G22: 0 | H22: 38102236 | I22: 0 | J22: 37738112 | K22: 0 | L22: 1895362 | M22: 0 | N22: 0 | O22: 0
A23: 131HUAXIN | C23: CTY TNHH DING XIN INDUSTRIAL (CTY TNHH HUA XIN CŨ) | D23: 366983560 | E23: 0 | F23: 0 | G23: 0 | H23: 48184416 | I23: 0 | J23: 74477232 | K23: 0 | L23: 340690744 | M23: 0 | N23: 0 | O23: 0
A24: 131JING | C24: CTY JING TZUAN FURNITURE CO.,LTD | D24: 227718338 | E24: 0 | F24: 0 | G24: 0 | H24: 0 | I24: 0 | J24: 0 | K24: 0 | L24: 227718338 | M24: 0 | N24: 0 | O24: 0
A25: 131PHONG | C25: CTY TNHH KIM PHONG | H25: 14271811 | I25: 0 | J25: 14271811 | K25: 0 | L25: 0 | M25: 0 | N25: 0 | O25: 0
A26: 131HAO | C26: CTY TNHH LONG HAO | D26: 18006428 | E26: 0 | F26: 0 | G26: 0 | H26: 0 | I26: 0 | J26: 0 | K26: 0 | L26: 18006428 | M26: 0 | N26: 0 | O26: 0
A27: 131LODE | C27: CTY TNHH LODE STAR | H27: 573810620 | I27: 0 | J27: 332061260 | K27: 0 | L27: 241749360 | M27: 0 | N27: 0 | O27: 0
A28: 131LT | C28: CTY TNHH MTV SX TM LÂM THỊNH | D28: 670729421 | E28: 0 | F28: 0 | G28: 0 | H28: 310974606 | I28: 0 | J28: 789481793 | K28: 0 | L28: 192222234 | M28: 0 | N28: 0 | O28: 0
A29: 131FURN | C29: CTY TNHH MAEVE FURN | D29: 0 | E29: 0 | F29: 0 | G29: 0 | H29: 9293324 | I29: 0 | J29: 8201520 | K29: 0 | L29: 1091804 | M29: 0 | N29: 0 | O29: 0
A30: 131TIEN | C30: CTY CP SX KD XNK MINH TIẾN | H30: 15631704 | I30: 0 | J30: 15631704 | K30: 0 | L30: 0 | M30: 0 | N30: 0 | O30: 0
A31: 131MS | C31: CTY TNHH MORI SHIGE | D31: 0 | E31: 0 | F31: 0 | G31: 0 | H31: 4606896 | I31: 0 | J31: 4606896 | K31: 0 | L31: 0 | M31: 0 | N31: 0 | O31: 0
A32: 131KY | C32: CTY TNHH NGHĨA KỲ | D32: 210935031 | E32: 0 | F32: 0 | G32: 0 | H32: 1604659328 | I32: 0 | J32: 1580510534 | K32: 0 | L32: 235083825 | M32: 0 | N32: 0 | O32: 0
A33: 131PDINH | C33: CTY TNHH NỘI THẤT GỖ PHÚ ĐỈNH | D33: 252504 | E33: 0 | F33: 0 | G33: 0 | H33: 2444818 | I33: 0 | J33: 2697322 | K33: 0 | L33: 0 | M33: 0 | N33: 0 | O33: 0
A34: 131HUAT | C34: CTY CP POH HUAT VN | D34: 4503168 | E34: 0 | F34: 0 | G34: 0 | H34: 21258720 | I34: 0 | J34: 20670984 | K34: 0 | L34: 5090904 | M34: 0 | N34: 0 | O34: 0
A35: 131SFA | C35: CTY TNHH SAN FA VN | D35: 6123600 | E35: 0 | F35: 0 | G35: 0 | H35: 18263092 | I35: 0 | J35: 24386692 | K35: 0 | L35: 0 | M35: 0 | N35: 0 | O35: 0
A36: 131SNGHE | C36: CTYTNHH SIÊU NGHỆ | D36: 821584069 | E36: 0 | F36: 0 | G36: 0 | H36: 0 | I36: 0 | J36: 0 | K36: 0 | L36: 821584069 | M36: 0 | N36: 0 | O36: 0
A37: 131THP | C37: CTY TNHH TM TAM HỢP PHÁT | D37: 1699946400 | E37: 0 | F37: 0 | G37: 0 | H37: 0 | I37: 0 | J37: 0 | K37: 0 | L37: 1699946400 | M37: 0 | N37: 0 | O37: 0
A38: 131TL | C38: CTY TNHH MTV THẮNG LÂM | D38: 387033948 | E38: 0 | F38: 0 | G38: 0 | H38: 0 | I38: 0 | J38: 0 | K38: 0 | L38: 387033948 | M38: 0 | N38: 0 | O38: 0
A39: 131TMBH | C39: CTY TNHH SX TM B H | D39: 57601406 | E39: 0 | F39: 0 | G39: 0 | H39: 0 | I39: 0 | J39: 0 | K39: 0 | L39: 57601406 | M39: 0 | N39: 0 | O39: 0
A40: 131TPP | C40: CTY TNHH THÀNH PHÚ PHÁT | D40: 39142810 | E40: 0 | F40: 0 | G40: 0 | H40: 755361294 | I40: 0 | J40: 794504104 | K40: 0 | L40: 0 | M40: 0 | N40: 0 | O40: 0
A41: 131TRDUC | C41: CTY CỔ PHẦN TRẦN ĐỨC | D41: 471056275 | E41: 0 | F41: 0 | G41: 0 | H41: 0 | I41: 0 | J41: 200000000 | K41: 0 | L41: 271056275 | M41: 0 | N41: 0 | O41: 0
A42: 131THANH | C42: CTY CỔ PHẦN TẬP ĐOÀN KỸ NGHỆ GỖ TRƯỜNG THÀNH | D42: 54832480 | E42: 0 | F42: 0 | G42: 0 | H42: 0 | I42: 0 | J42: 0 | K42: 0 | L42: 54832480 | M42: 0 | N42: 0 | O42: 0
A43: 131VC | C43: CTY TNHH MTV SX TM VẠN CHÍNH | D43: 0 | E43: 0 | F43: 0 | G43: 0 | H43: 67197384 | I43: 0 | J43: 67197384 | K43: 0 | L43: 0 | M43: 0 | N43: 0 | O43: 0
A44: 131HANG | C44: CTY TNHH WAN LI HANG (VN) | H44: 58913568 | I44: 0 | J44: 58913568 | K44: 0 | L44: 0 | M44: 0 | N44: 0 | O44: 0
A45: 131WOODEN | C45: CTY TNHH WOODWORTH WOODEN (VN) | D45: 8207136 | E45: 0 | F45: 0 | G45: 0 | H45: 10036677 | I45: 0 | J45: 18243813 | K45: 0 | L45: 0 | M45: 0 | N45: 0 | O45: 0
A46: 131SUN | C46: CTY TNHH MTV Tân King Sun | D46: 61209250 | E46: 0 | F46: 0 | G46: 0 | H46: 0 | I46: 0 | J46: 0 | K46: 0 | L46: 61209250 | M46: 0 | N46: 0 | O46: 0
A47: 131VT | C47: CÔNG TY TNHH VĨNH THÀNH ENTERPRISE | D47: 2007720 | E47: 0 | F47: 0 | G47: 0 | H47: 2023164 | I47: 0 | J47: 4030884 | K47: 0 | L47: 0 | M47: 0 | N47: 0 | O47: 0
A48: 131THAM | C48: CÔNG TY TNHH SẢN XUẤT THƯƠNG MẠI TRƯỜNG THÂM | D48: 177714000 | E48: 0 | F48: 0 | G48: 0 | H48: 0 | I48: 0 | J48: 0 | K48: 0 | L48: 177714000 | M48: 0 | N48: 0 | O48: 0
A49: 131GHT | C49: CÔNG TY TNHH CHẾ BIẾN GỖ HIỆP THÀNH | H49: 27119059 | I49: 0 | J49: 27119059 | K49: 0 | L49: 0 | M49: 0 | N49: 0 | O49: 0
A50: 131YC | C50: CÔNG TY TNHH NỘI THẤT YOU CHUANG VIỆT NAM | D50: 11093436 | E50: 0 | F50: 0 | G50: 0 | H50: 41382036 | I50: 0 | J50: 49366800 | K50: 0 | L50: 3108672 | M50: 0 | N50: 0 | O50: 0
A51: 131CBG | C51: CÔNG TY TNHH CBG HOÀNG NGUYÊN | H51: 29953800 | I51: 0 | J51: 29953800 | K51: 0 | L51: 0 | M51: 0 | N51: 0 | O51: 0
A52: 131VLP | C52: CÔNG TY TNHH THƯƠNG MẠI SX GỖ VIỆT LONG PHÁT | H52: 71632339 | I52: 0 | J52: 71632339 | K52: 0 | L52: 0 | M52: 0 | N52: 0 | O52: 0
A53: 131BĐH | C53: CÔNG TY TNHH SẢN XUẤT THƯƠNG MẠI BẢO ĐỆ HÂN | H53: 184479228 | I53: 0 | J53: 184479228 | K53: 0 | L53: 0 | M53: 0 | N53: 0 | O53: 0
A54: 131WOODPARK | C54: CÔNG TY TNHH WOODPARK FURNITURE VIỆT NAM | H54: 80457516 | I54: 0 | J54: 80457516 | K54: 0 | L54: 0 | M54: 0 | N54: 0 | O54: 0
A55: 131NTKT | C55: CÔNG TY TNHH NGỌC THẠCH KHẢI THÀNH | H55: 81697556 | I55: 0 | J55: 81697556 | K55: 0 | L55: 0 | M55: 0 | N55: 0 | O55: 0
A56: 131HPHONG | C56: CÔNG TY TNHH HÀO PHONG I | H56: 15886800 | I56: 0 | J56: 15536880 | K56: 0 | L56: 349920 | M56: 0 | N56: 0 | O56: 0
A57: 131GHL | C57: CÔNG TY TNHH NỘI THẤT GỖ HIẾU LONG | H57: 2052875 | I57: 0 | J57: 0 | K57: 0 | L57: 2052875 | M57: 0 | N57: 0 | O57: 0
A58: 131SONNY | C58: CÔNG TY TNHH SONNY INDUSTRIAL (VIETNAM) | H58: 13899600 | I58: 0 | J58: 0 | K58: 0 | L58: 13899600 | M58: 0 | N58: 0 | O58: 0
A59: 131SHUN | C59: CÔNG TY TNHH XIN SHUN YUE | H59: 1210000 | I59: 0 | J59: 0 | K59: 0 | L59: 1210000 | M59: 0 | N59: 0 | O59: 0
A60: 131KTH | C60: CÔNG TY TNHH MỘT THÀNH VIÊN THƯƠNG MẠI DỊCH VỤ SẢN XUẤT KIM THÀNH HƯNG | H60: 8800000 | I60: 0 | J60: 0 | K60: 0 | L60: 8800000 | M60: 0 | N60: 0 | O60: 0
A61: 1331 | B61: 進項增值稅-商品.勞務 | C61: Thuế GTGT được khấu trừ của hàng hóa, DV | D61: 0 | E61: 0 | F61: 0 | G61: 0 | H61: 406601825 | I61: 0 | J61: 406601825 | K61: 0 | L61: 0 | M61: 0 | N61: 0 | O61: 0
A62: 1521 | B62: 原物料 | C62: NVL chính | D62: 889041511 | E62: 0 | F62: 0 | G62: 0 | H62: 1338120000 | I62: 0 | J62: 2227161511 | K62: 0 | L62: 0 | M62: 0 | N62: 0 | O62: 0
A63: 1522 | B63: 原物料 | C63: NVL chính phụ | D63: 37283451 | E63: 0 | F63: 0 | G63: 0 | H63: 205914316 | I63: 0 | J63: 243197767 | K63: 0 | L63: 0 | M63: 0 | N63: 0 | O63: 0
A64: 1541 | B64: 在製品 | C64: Thành phẩm dở dang | D64: 717137083 | E64: 0 | F64: 0 | G64: 0 | H64: 4.4073187e+09 | I64: 0 | J64: 5.1244558e+09 | K64: 0 | L64: 0 | M64: 0 | N64: 0 | O64: 0
A65: 1551 | B65: 成品入倉 | C65: Thành phẩm | D65: 220092793 | E65: 0 | F65: 0 | G65: 0 | H65: 4.2176998e+09 | I65: 0 | J65: 4437792592 | K65: 0 | L65: 0 | M65: 0 | N65: 0 | O65: 0
A66: 1561 | B66: 商品 | C66: Hàng hóa | D66: 0 | E66: 0 | F66: 0 | G66: 0 | H66: 1475840159 | I66: 0 | J66: 1475840159 | K66: 0 | L66: 0 | M66: 0 | N66: 0 | O66: 0
A67: 2112 | B67: 機械與設備 | C67: Máy móc, thiết bị | D67: 654809273 | E67: 0 | F67: 0 | G67: 0 | H67: 0 | I67: 0 | J67: 0 | K67: 0 | L67: 654809273 | M67: 0 | N67: 0 | O67: 0
A68: 2113 | B68: 運輸設備 | C68: Phương tiện vận tải, truyền dẫn | D68: 2862430000 | E68: 0 | F68: 0 | G68: 0 | H68: 0 | I68: 0 | J68: 0 | K68: 0 | L68: 2862430000 | M68: 0 | N68: 0 | O68: 0
A69: 2141 | B69: 有形固定資產攤提 | C69: Hao mòn TSCĐ hữu hình | D69: 0 | E69: 0 | F69: 1913196788 | G69: 0 | H69: 0 | I69: 0 | J69: 429287796 | K69: 0 | L69: 0 | M69: 0 | N69: 2342484584 | O69: 0
A70: 2293 | B70: 備抵壞帳 | C70: Dự phòng phải thu khó đòi | D70: 0 | E70: 0 | F70: 3766404730 | G70: 0 | H70: 0 | I70: 0 | J70: 0 | K70: 0 | L70: 0 | M70: 0 | N70: 3766404730 | O70: 0
A71: 2294 | B71: 備抵庫存跌價 | C71: Dự phòng giảm giá hàng tồn kho | D71: 0 | E71: 0 | F71: 0 | G71: 0 | H71: 0 | I71: 0 | J71: 0 | K71: 0 | L71: 0 | M71: 0 | N71: 0 | O71: 0
A72: 2421 | B72: 預付費用(少于12个月) | C72: Chi phí trả trước ngắn hạn (dưới 12 tháng) | D72: 114580506 | E72: 0 | F72: 0 | G72: 0 | H72: 794961321 | I72: 0 | J72: 892814468 | K72: 0 | L72: 16727359 | M72: 0 | N72: 0 | O72: 0
A73: 2422 | B73: 預付費用(超过12个月) | C73: Chi phí trả trước dài hạn (trên 12 tháng) | D73: 6655971 | E73: 0 | F73: 0 | G73: 0 | H73: 3200000 | I73: 0 | J73: 3885648 | K73: 0 | L73: 5970323 | M73: 0 | N73: 0 | O73: 0
A74: 331ETEMAL | C74: ETERNAL MATERIALS CO., LTD | D74: 0 | E74: 0 | F74: 5049518508 | G74: 197710.2 | H74: 0 | I74: 0 | J74: 0 | K74: 0 | L74: 0 | M74: 0 | N74: 5049518508 | O74: 197710.2
A75: 331ORKING | C75: ORKING CO. TLD | D75: 0 | E75: 0 | F75: 629811292 | G75: 24659.8 | H75: 0 | I75: 0 | J75: 0 | K75: 0 | L75: 0 | M75: 0 | N75: 629811292 | O75: 24659.8
A76: 331WINNER | C76: MULTIPLE WINNER CO.,TLD | D76: 0 | E76: 0 | F76: 853097296 | G76: 33402.4 | H76: 0 | I76: 0 | J76: 0 | K76: 0 | L76: 0 | M76: 0 | N76: 853097296 | O76: 33402.4
A77: 331AKP | C77: CTY TNHH MTV TRẠM XĂNG DẦU AN KHÁNH PHÁT | D77: 0 | E77: 0 | F77: 3744630 | G77: 0 | H77: 42864175 | I77: 0 | J77: 44132585 | K77: 0 | L77: 0 | M77: 0 | N77: 5013040 | O77: 0
A78: 331CH | C78: CTY TNHH TM DV SX CẢNH HOÀNH | D78: 0 | E78: 0 | F78: 75652500 | G78: 0 | H78: 151881748 | I78: 0 | J78: 76229248 | K78: 0 | L78: 0 | M78: 0 | N78: 0 | O78: 0
A79: 331CPA | C79: CTY TNHH KIỂM TOÁN CPA | D79: 0 | E79: 0 | F79: 0 | G79: 0 | H79: 22680000 | I79: 0 | J79: 22680000 | K79: 0 | L79: 0 | M79: 0 | N79: 0 | O79: 0
A80: 331NAM | C80: CTY TNHH MTV DV BẢO VỆ ĐẠI HOÀNG NAM | D80: 0 | E80: 0 | F80: 18751824 | G80: 0 | H80: 229406688 | I80: 0 | J80: 210654864 | K80: 0 | L80: 0 | M80: 0 | N80: 0 | O80: 0
A81: 331DPD | C81: CTY TNHH SX TM ĐẠI PHÚ ĐIỀN | D81: 0 | E81: 0 | F81: 29700000 | G81: 0 | H81: 310911491 | I81: 0 | J81: 286341491 | K81: 0 | L81: 0 | M81: 0 | N81: 5130000 | O81: 0
A82: 331HOAI | C82: CTY CỔ PHẦN Ô TÔ GIANG HOÀI | H82: 0 | I82: 0 | J82: 3259000 | K82: 0 | L82: 0 | M82: 0 | N82: 3259000 | O82: 0
A83: 331HP | C83: CTY TNHH HẢI PHONG | D83: 0 | E83: 0 | F83: 8478000 | G83: 0 | H83: 24680160 | I83: 0 | J83: 16839360 | K83: 0 | L83: 0 | M83: 0 | N83: 637200 | O83: 0
A84: 331TLAM | C84: CTY TNHH MTV THẮNG LÂM | D84: 0 | E84: 0 | F84: 288053263 | G84: 0 | H84: 0 | I84: 0 | J84: 0 | K84: 0 | L84: 0 | M84: 0 | N84: 288053263 | O84: 0
A85: 331TLN | C85: CTY TNHH MTV TRẦN LÊ NAM | D85: 0 | E85: 0 | F85: 0 | G85: 0 | H85: 1046862299 | I85: 0 | J85: 1.0468623e+09 | K85: 0 | L85: 0 | M85: 0 | N85: 0 | O85: 0
A86: 331BNP | C86: CTY TNHH SX TM BÌNH NGUYÊN PHÁT | D86: 0 | E86: 0 | F86: 10800000 | G86: 0 | H86: 75600000 | I86: 0 | J86: 64800000 | K86: 0 | L86: 0 | M86: 0 | N86: 0 | O86: 0
A87: 331HAI | C87: CTY TNHH THACO AUTO BÌNH DƯƠNG (CTY TRƯỜNG HẢI-BD CŨ) | H87: 0 | I87: 0 | J87: 9478030 | K87: 0 | L87: 0 | M87: 0 | N87: 9478030 | O87: 0
A88: 331VNPT | C88: TTKD VNPT | D88: 0 | E88: 0 | F88: 0 | G88: 0 | H88: 3350280 | I88: 0 | J88: 3350280 | K88: 0 | L88: 0 | M88: 0 | N88: 0 | O88: 0
A89: 331TLONG | C89: CÔNG TY TNHH THÂM LONG | D89: 0 | E89: 0 | F89: 752868800 | G89: 0 | H89: 1748313300 | I89: 0 | J89: 1483863100 | K89: 0 | L89: 0 | M89: 0 | N89: 488418600 | O89: 0
A90: 331HTRU | C90: CÔNG TY TNHH MỘT THÀNH VIÊN HỢP TRỤ | D90: 0 | E90: 0 | F90: 376140529 | G90: 0 | H90: 1568289146 | I90: 0 | J90: 1450801705 | K90: 0 | L90: 0 | M90: 0 | N90: 258653088 | O90: 0
A91: 331HB | C91: CÔNG TY TNHH CÔNG NGHỆ PHÁT TRIỂN HOÀN BÍCH | D91: 0 | E91: 0 | F91: 0 | G91: 0 | H91: 8316000 | I91: 0 | J91: 8316000 | K91: 0 | L91: 0 | M91: 0 | N91: 0 | O91: 0
A92: 331BL | C92: Tổng Công Ty Cổ Phần Bảo Hiểm Bảo Long - Công Ty Bảo Hiểm Bảo Long Bình Dương | D92: 0 | E92: 0 | F92: 0 | G92: 0 | H92: 9900000 | I92: 0 | J92: 9900000 | K92: 0 | L92: 0 | M92: 0 | N92: 0 | O92: 0
A93: 331KHQ | C93: CÔNG TY TNHH KIM HÀO QUÁN | H93: 2817504 | I93: 0 | J93: 2817504 | K93: 0 | L93: 0 | M93: 0 | N93: 0 | O93: 0
A94: 331TECH | C94: Tổng Công Ty Cổ Phần Bảo Hiểm Bảo Long - Công Ty Bảo Hiểm Bảo Long Bình Dương | H94: 2970000 | I94: 0 | J94: 2970000 | K94: 0 | L94: 0 | M94: 0 | N94: 0 | O94: 0
A95: 331AHP | C95: CÔNG TY TNHH MỘT THÀNH VIÊN THƯƠNG MẠI DỊCH VỤ ÁNH HOÀNG PHÁT | H95: 1750000 | I95: 0 | J95: 1750000 | K95: 0 | L95: 0 | M95: 0 | N95: 0 | O95: 0
A96: 331TT | C96: CÔNG TY TNHH KINH DOANH ĐỒ GỖ TẤN TÀI | H96: 1350000 | I96: 0 | J96: 1350000 | K96: 0 | L96: 0 | M96: 0 | N96: 0 | O96: 0
A97: 331TOYOTA | C97: CÔNG TY TNHH TOYOTA THUẬN AN | H97: 0 | I97: 0 | J97: 5484266 | K97: 0 | L97: 0 | M97: 0 | N97: 5484266 | O97: 0
A98: 331VCN | C98: CHI NHÁNH CÔNG TY TNHH VŨ CHI NAM - TRUNG TÂM ĐĂNG KIỂM XE CƠ GIỚI 61-09D | H98: 10590637 | I98: 0 | J98: 10590637 | K98: 0 | L98: 0 | M98: 0 | N98: 0 | O98: 0
A99: 331NĐT | C99: CÔNG TY TNHH SX TM DV NAM ĐẠI THẮNG | H99: 1155000 | I99: 0 | J99: 1155000 | K99: 0 | L99: 0 | M99: 0 | N99: 0 | O99: 0
A100: 331HUNG | C100: CÔNG TY TNHH MTV THẠCH CAO VINH HƯNG | H100: 0 | I100: 0 | J100: 4590000 | K100: 0 | L100: 0 | M100: 0 | N100: 4590000 | O100: 0
A101: 331LP | C101: CÔNG TY TNHH TMDV SX LINH PHÁT | H101: 0 | I101: 0 | J101: 107683200 | K101: 0 | L101: 0 | M101: 0 | N101: 107683200 | O101: 0
...

Sheet 2293
C1: 44196 | D1: =SUBTOTAL(9,D5:D211) -> 13579452926 | F1: =SUM(F5:F211) -> 6866289494 | G1: =SUM(G5:G211) -> 865623692 | H1: =SUM(H5:H211) -> 4621022128 | I1: =SUM(I5:I211) -> 438479589 | J1: =SUM(J5:J211) -> 788038023 | K1: =SUM(K5:K211) -> 3.6651719e+09 | L1: trích lập của KT năm 2020
A2: Tên khách hàng | B2: Số Hóa đơn | C2: Ngày Hóa đơn | D2: Số tiền | E2: Phân tích tuổi nợ | K2: Tổng trích lập dự phòng
E3: Quá hạn (tháng) | F3: Quá hạn dưới 6 tháng | G3: 6 tháng - 1 năm | H3: 1 năm - 2 năm | I3: 2 năm - 3 năm | J3: từ 3 năm trở lên
F4: 0 | G4: 0.3 | H4: 0.5 | I4: 0.7 | J4: 1
A5: Phải thu - Công Ty TNHH Hua Xin | B5: 0000267 | C5: 43832 | D5: 18179700 | E5: =($C$1-C5)/30 -> 12.133333 | F5: =IF(E5<6,D5,0) -> 0 | G5: =IF(AND(E5>=6,E5<12),D5,0) -> 0 | H5: =IF(AND(E5>=12,E5<24),D5,0) -> 18179700 | I5: =IF(AND(E5>=24,E5<36),D5,0) -> 0 | J5: =IF(E5>=36,D5,0) -> 0 | K5: =F5*$F$4+G5*$G$4+H5*$H$4+I5*$I$4+J5*$J$4 -> 9089850
A6: Phải thu - Công Ty TNHH Hua Xin | B6: 0000267 | C6: 43832 | D6: 1817970 | E6: =($C$1-C6)/30 -> 12.133333 | F6: =IF(E6<6,D6,0) -> 0 | G6: =IF(AND(E6>=6,E6<12),D6,0) -> 0 | H6: =IF(AND(E6>=12,E6<24),D6,0) -> 1817970 | I6: =IF(AND(E6>=24,E6<36),D6,0) -> 0 | J6: =IF(E6>=36,D6,0) -> 0 | K6: =F6*$F$4+G6*$G$4+H6*$H$4+I6*$I$4+J6*$J$4 -> 908985
A7: Phải thu - Công Ty TNHH Hua Xin | B7: 0000307 | C7: 43887 | D7: 47676330 | E7: =($C$1-C7)/30 -> 10.3 | F7: =IF(E7<6,D7,0) -> 0 | G7: =IF(AND(E7>=6,E7<12),D7,0) -> 47676330 | H7: =IF(AND(E7>=12,E7<24),D7,0) -> 0 | I7: =IF(AND(E7>=24,E7<36),D7,0) -> 0 | J7: =IF(E7>=36,D7,0) -> 0 | K7: =F7*$F$4+G7*$G$4+H7*$H$4+I7*$I$4+J7*$J$4 -> 14302899
A8: Phải thu - Công Ty TNHH Hua Xin | B8: 0000307 | C8: 43887 | D8: 4767633 | E8: =($C$1-C8)/30 -> 10.3 | F8: =IF(E8<6,D8,0) -> 0 | G8: =IF(AND(E8>=6,E8<12),D8,0) -> 4767633 | H8: =IF(AND(E8>=12,E8<24),D8,0) -> 0 | I8: =IF(AND(E8>=24,E8<36),D8,0) -> 0 | J8: =IF(E8>=36,D8,0) -> 0 | K8: =F8*$F$4+G8*$G$4+H8*$H$4+I8*$I$4+J8*$J$4 -> 1430289.9
A9: Phải thu - Công Ty TNHH Hua Xin | B9: 0000355 | C9: 43917 | D9: 89319600 | E9: =($C$1-C9)/30 -> 9.3 | F9: =IF(E9<6,D9,0) -> 0 | G9: =IF(AND(E9>=6,E9<12),D9,0) -> 89319600 | H9: =IF(AND(E9>=12,E9<24),D9,0) -> 0 | I9: =IF(AND(E9>=24,E9<36),D9,0) -> 0 | J9: =IF(E9>=36,D9,0) -> 0 | K9: =F9*$F$4+G9*$G$4+H9*$H$4+I9*$I$4+J9*$J$4 -> 26795880
A10: Phải thu - Công Ty TNHH Hua Xin | B10: 0000355 | C10: 43917 | D10: 8931960 | E10: =($C$1-C10)/30 -> 9.3 | F10: =IF(E10<6,D10,0) -> 0 | G10: =IF(AND(E10>=6,E10<12),D10,0) -> 8931960 | H10: =IF(AND(E10>=12,E10<24),D10,0) -> 0 | I10: =IF(AND(E10>=24,E10<36),D10,0) -> 0 | J10: =IF(E10>=36,D10,0) -> 0 | K10: =F10*$F$4+G10*$G$4+H10*$H$4+I10*$I$4+J10*$J$4 -> 2679588
A11: Phải thu - Công Ty TNHH Hua Xin | B11: 785 | C11: 43479 | D11: 3731440 | E11: =($C$1-C11)/30 -> 23.9 | F11: =IF(E11<6,D11,0) -> 0 | G11: =IF(AND(E11>=6,E11<12),D11,0) -> 0 | H11: =IF(AND(E11>=12,E11<24),D11,0) -> 3731440 | I11: =IF(AND(E11>=24,E11<36),D11,0) -> 0 | J11: =IF(E11>=36,D11,0) -> 0 | K11: =F11*$F$4+G11*$G$4+H11*$H$4+I11*$I$4+J11*$J$4 -> 1865720
A12: Phải thu - Công Ty TNHH Hua Xin | B12: 785 | C12: 43479 | D12: 373144 | E12: =($C$1-C12)/30 -> 23.9 | F12: =IF(E12<6,D12,0) -> 0 | G12: =IF(AND(E12>=6,E12<12),D12,0) -> 0 | H12: =IF(AND(E12>=12,E12<24),D12,0) -> 373144 | I12: =IF(AND(E12>=24,E12<36),D12,0) -> 0 | J12: =IF(E12>=36,D12,0) -> 0 | K12: =F12*$F$4+G12*$G$4+H12*$H$4+I12*$I$4+J12*$J$4 -> 186572
A13: Phải thu - Công Ty TNHH Hua Xin | B13: 835 | C13: 43522 | D13: 75066160 | E13: =($C$1-C13)/30 -> 22.466667 | F13: =IF(E13<6,D13,0) -> 0 | G13: =IF(AND(E13>=6,E13<12),D13,0) -> 0 | H13: =IF(AND(E13>=12,E13<24),D13,0) -> 75066160 | I13: =IF(AND(E13>=24,E13<36),D13,0) -> 0 | J13: =IF(E13>=36,D13,0) -> 0 | K13: =F13*$F$4+G13*$G$4+H13*$H$4+I13*$I$4+J13*$J$4 -> 37533080
A14: Phải thu - Công Ty TNHH Hua Xin | B14: 835 | C14: 43522 | D14: 7506616 | E14: =($C$1-C14)/30 -> 22.466667 | F14: =IF(E14<6,D14,0) -> 0 | G14: =IF(AND(E14>=6,E14<12),D14,0) -> 0 | H14: =IF(AND(E14>=12,E14<24),D14,0) -> 7506616 | I14: =IF(AND(E14>=24,E14<36),D14,0) -> 0 | J14: =IF(E14>=36,D14,0) -> 0 | K14: =F14*$F$4+G14*$G$4+H14*$H$4+I14*$I$4+J14*$J$4 -> 3753308
A15: Phải thu - Công Ty TNHH Hua Xin | B15: 0000850 | C15: 43549 | D15: 7062240 | E15: =($C$1-C15)/30 -> 21.566667 | F15: =IF(E15<6,D15,0) -> 0 | G15: =IF(AND(E15>=6,E15<12),D15,0) -> 0 | H15: =IF(AND(E15>=12,E15<24),D15,0) -> 7062240 | I15: =IF(AND(E15>=24,E15<36),D15,0) -> 0 | J15: =IF(E15>=36,D15,0) -> 0 | K15: =F15*$F$4+G15*$G$4+H15*$H$4+I15*$I$4+J15*$J$4 -> 3531120
A16: Phải thu - Công Ty TNHH Hua Xin | B16: 0000850 | C16: 43549 | D16: 706224 | E16: =($C$1-C16)/30 -> 21.566667 | F16: =IF(E16<6,D16,0) -> 0 | G16: =IF(AND(E16>=6,E16<12),D16,0) -> 0 | H16: =IF(AND(E16>=12,E16<24),D16,0) -> 706224 | I16: =IF(AND(E16>=24,E16<36),D16,0) -> 0 | J16: =IF(E16>=36,D16,0) -> 0 | K16: =F16*$F$4+G16*$G$4+H16*$H$4+I16*$I$4+J16*$J$4 -> 353112
A17: Phải thu - Công Ty TNHH Hua Xin | B17: 0 | C17: 43466 | D17: 57926880 | E17: =($C$1-C17)/30 -> 24.333333 | F17: =IF(E17<6,D17,0) -> 0 | G17: =IF(AND(E17>=6,E17<12),D17,0) -> 0 | H17: =IF(AND(E17>=12,E17<24),D17,0) -> 0 | I17: =IF(AND(E17>=24,E17<36),D17,0) -> 57926880 | J17: =IF(E17>=36,D17,0) -> 0 | K17: =F17*$F$4+G17*$G$4+H17*$H$4+I17*$I$4+J17*$J$4 -> 40548816
A18: Phải thu - Công Ty TNHH Hua Xin | B18: 0 | C18: 43466 | D18: 68322144 | E18: =($C$1-C18)/30 -> 24.333333 | F18: =IF(E18<6,D18,0) -> 0 | G18: =IF(AND(E18>=6,E18<12),D18,0) -> 0 | H18: =IF(AND(E18>=12,E18<24),D18,0) -> 0 | I18: =IF(AND(E18>=24,E18<36),D18,0) -> 68322144 | J18: =IF(E18>=36,D18,0) -> 0 | K18: =F18*$F$4+G18*$G$4+H18*$H$4+I18*$I$4+J18*$J$4 -> 47825501
A19: Phải thu - Công Ty TNHH Hua Xin | B19: 0 | C19: 43466 | D19: 312230565 | E19: =($C$1-C19)/30 -> 24.333333 | F19: =IF(E19<6,D19,0) -> 0 | G19: =IF(AND(E19>=6,E19<12),D19,0) -> 0 | H19: =IF(AND(E19>=12,E19<24),D19,0) -> 0 | I19: =IF(AND(E19>=24,E19<36),D19,0) -> 312230565 | J19: =IF(E19>=36,D19,0) -> 0 | K19: =F19*$F$4+G19*$G$4+H19*$H$4+I19*$I$4+J19*$J$4 -> 2.185614e+08
A20: Phải thu - Công Ty TNHH Hua Xin | B20: 0000900 | C20: 43581 | D20: 336311154 | E20: =($C$1-C20)/30 -> 20.5 | F20: =IF(E20<6,D20,0) -> 0 | G20: =IF(AND(E20>=6,E20<12),D20,0) -> 0 | H20: =IF(AND(E20>=12,E20<24),D20,0) -> 336311154 | I20: =IF(AND(E20>=24,E20<36),D20,0) -> 0 | J20: =IF(E20>=36,D20,0) -> 0 | K20: =F20*$F$4+G20*$G$4+H20*$H$4+I20*$I$4+J20*$J$4 -> 168155577
A21: Phải thu - Công Ty TNHH Hua Xin | B21: 0000900 | C21: 43581 | D21: 33631115 | E21: =($C$1-C21)/30 -> 20.5 | F21: =IF(E21<6,D21,0) -> 0 | G21: =IF(AND(E21>=6,E21<12),D21,0) -> 0 | H21: =IF(AND(E21>=12,E21<24),D21,0) -> 33631115 | I21: =IF(AND(E21>=24,E21<36),D21,0) -> 0 | J21: =IF(E21>=36,D21,0) -> 0 | K21: =F21*$F$4+G21*$G$4+H21*$H$4+I21*$I$4+J21*$J$4 -> 16815558
A22: Phải thu - Công Ty TNHH Hua Xin | B22: 0000960 | C22: 43614 | D22: 118888525 | E22: =($C$1-C22)/30 -> 19.4 | F22: =IF(E22<6,D22,0) -> 0 | G22: =IF(AND(E22>=6,E22<12),D22,0) -> 0 | H22: =IF(AND(E22>=12,E22<24),D22,0) -> 118888525 | I22: =IF(AND(E22>=24,E22<36),D22,0) -> 0 | J22: =IF(E22>=36,D22,0) -> 0 | K22: =F22*$F$4+G22*$G$4+H22*$H$4+I22*$I$4+J22*$J$4 -> 59444262
A23: Phải thu - Công Ty TNHH Hua Xin | B23: 0000960 | C23: 43614 | D23: 11888853 | E23: =($C$1-C23)/30 -> 19.4 | F23: =IF(E23<6,D23,0) -> 0 | G23: =IF(AND(E23>=6,E23<12),D23,0) -> 0 | H23: =IF(AND(E23>=12,E23<24),D23,0) -> 11888853 | I23: =IF(AND(E23>=24,E23<36),D23,0) -> 0 | J23: =IF(E23>=36,D23,0) -> 0 | K23: =F23*$F$4+G23*$G$4+H23*$H$4+I23*$I$4+J23*$J$4 -> 5944426.5
A24: Phải thu - Công Ty TNHH Hua Xin | B24: 57 | C24: 43675 | D24: 506710460 | E24: =($C$1-C24)/30 -> 17.366667 | F24: =IF(E24<6,D24,0) -> 0 | G24: =IF(AND(E24>=6,E24<12),D24,0) -> 0 | H24: =IF(AND(E24>=12,E24<24),D24,0) -> 506710460 | I24: =IF(AND(E24>=24,E24<36),D24,0) -> 0 | J24: =IF(E24>=36,D24,0) -> 0 | K24: =F24*$F$4+G24*$G$4+H24*$H$4+I24*$I$4+J24*$J$4 -> 253355230
A25: Phải thu - Công Ty TNHH Hua Xin | B25: 57 | C25: 43675 | D25: 50671046 | E25: =($C$1-C25)/30 -> 17.366667 | F25: =IF(E25<6,D25,0) -> 0 | G25: =IF(AND(E25>=6,E25<12),D25,0) -> 0 | H25: =IF(AND(E25>=12,E25<24),D25,0) -> 50671046 | I25: =IF(AND(E25>=24,E25<36),D25,0) -> 0 | J25: =IF(E25>=36,D25,0) -> 0 | K25: =F25*$F$4+G25*$G$4+H25*$H$4+I25*$I$4+J25*$J$4 -> 25335523
A26: Phải thu - Công Ty TNHH Hua Xin | B26: 129 | C26: 43733 | D26: 286310226 | E26: =($C$1-C26)/30 -> 15.433333 | F26: =IF(E26<6,D26,0) -> 0 | G26: =IF(AND(E26>=6,E26<12),D26,0) -> 0 | H26: =IF(AND(E26>=12,E26<24),D26,0) -> 286310226 | I26: =IF(AND(E26>=24,E26<36),D26,0) -> 0 | J26: =IF(E26>=36,D26,0) -> 0 | K26: =F26*$F$4+G26*$G$4+H26*$H$4+I26*$I$4+J26*$J$4 -> 143155113
A27: Phải thu - Công Ty TNHH Hua Xin | B27: 129 | C27: 43733 | D27: 28631023 | E27: =($C$1-C27)/30 -> 15.433333 | F27: =IF(E27<6,D27,0) -> 0 | G27: =IF(AND(E27>=6,E27<12),D27,0) -> 0 | H27: =IF(AND(E27>=12,E27<24),D27,0) -> 28631023 | I27: =IF(AND(E27>=24,E27<36),D27,0) -> 0 | J27: =IF(E27>=36,D27,0) -> 0 | K27: =F27*$F$4+G27*$G$4+H27*$H$4+I27*$I$4+J27*$J$4 -> 14315512
A28: Phải thu - Công Ty TNHH Hua Xin | B28: 162 | C28: 43764 | D28: 324885600 | E28: =($C$1-C28)/30 -> 14.4 | F28: =IF(E28<6,D28,0) -> 0 | G28: =IF(AND(E28>=6,E28<12),D28,0) -> 0 | H28: =IF(AND(E28>=12,E28<24),D28,0) -> 324885600 | I28: =IF(AND(E28>=24,E28<36),D28,0) -> 0 | J28: =IF(E28>=36,D28,0) -> 0 | K28: =F28*$F$4+G28*$G$4+H28*$H$4+I28*$I$4+J28*$J$4 -> 162442800
A29: Phải thu - Công Ty TNHH Hua Xin | B29: 162 | C29: 43764 | D29: 32488560 | E29: =($C$1-C29)/30 -> 14.4 | F29: =IF(E29<6,D29,0) -> 0 | G29: =IF(AND(E29>=6,E29<12),D29,0) -> 0 | H29: =IF(AND(E29>=12,E29<24),D29,0) -> 32488560 | I29: =IF(AND(E29>=24,E29<36),D29,0) -> 0 | J29: =IF(E29>=36,D29,0) -> 0 | K29: =F29*$F$4+G29*$G$4+H29*$H$4+I29*$I$4+J29*$J$4 -> 16244280
A30: Phải thu - Công Ty TNHH Hua Xin | B30: 206 | C30: 43796 | D30: 10468670 | E30: =($C$1-C30)/30 -> 13.333333 | F30: =IF(E30<6,D30,0) -> 0 | G30: =IF(AND(E30>=6,E30<12),D30,0) -> 0 | H30: =IF(AND(E30>=12,E30<24),D30,0) -> 10468670 | I30: =IF(AND(E30>=24,E30<36),D30,0) -> 0 | J30: =IF(E30>=36,D30,0) -> 0 | K30: =F30*$F$4+G30*$G$4+H30*$H$4+I30*$I$4+J30*$J$4 -> 5234335
A31: Phải thu - Công Ty TNHH Hua Xin | B31: 206 | C31: 43796 | D31: 1046867 | E31: =($C$1-C31)/30 -> 13.333333 | F31: =IF(E31<6,D31,0) -> 0 | G31: =IF(AND(E31>=6,E31<12),D31,0) -> 0 | H31: =IF(AND(E31>=12,E31<24),D31,0) -> 1046867 | I31: =IF(AND(E31>=24,E31<36),D31,0) -> 0 | J31: =IF(E31>=36,D31,0) -> 0 | K31: =F31*$F$4+G31*$G$4+H31*$H$4+I31*$I$4+J31*$J$4 -> 523433.5
A32: Phải thu - Công Ty TNHH Hua Xin | B32: 236 | C32: 43823 | D32: 18240710 | E32: =($C$1-C32)/30 -> 12.433333 | F32: =IF(E32<6,D32,0) -> 0 | G32: =IF(AND(E32>=6,E32<12),D32,0) -> 0 | H32: =IF(AND(E32>=12,E32<24),D32,0) -> 18240710 | I32: =IF(AND(E32>=24,E32<36),D32,0) -> 0 | J32: =IF(E32>=36,D32,0) -> 0 | K32: =F32*$F$4+G32*$G$4+H32*$H$4+I32*$I$4+J32*$J$4 -> 9120355
A33: Phải thu - Công Ty TNHH Hua Xin | B33: 236 | C33: 43823 | D33: 1824071 | E33: =($C$1-C33)/30 -> 12.433333 | F33: =IF(E33<6,D33,0) -> 0 | G33: =IF(AND(E33>=6,E33<12),D33,0) -> 0 | H33: =IF(AND(E33>=12,E33<24),D33,0) -> 1824071 | I33: =IF(AND(E33>=24,E33<36),D33,0) -> 0 | J33: =IF(E33>=36,D33,0) -> 0 | K33: =F33*$F$4+G33*$G$4+H33*$H$4+I33*$I$4+J33*$J$4 -> 912035.5
A34: Phải thu - Công Ty TNHH Hua Xin | C34: 43101 | D34: 380848114 | E34: =($C$1-C34)/30 -> 36.5 | F34: =IF(E34<6,D34,0) -> 0 | G34: =IF(AND(E34>=6,E34<12),D34,0) -> 0 | H34: =IF(AND(E34>=12,E34<24),D34,0) -> 0 | I34: =IF(AND(E34>=24,E34<36),D34,0) -> 0 | J34: =IF(E34>=36,D34,0) -> 380848114 | K34: =F34*$F$4+G34*$G$4+H34*$H$4+I34*$I$4+J34*$J$4 -> 380848114
A35: Công Ty TNHH TM Tam Hợp Phát | C35: 43678 | D35: 2299946400 | E35: =($C$1-C35)/30 -> 17.266667 | F35: =IF(E35<6,D35,0) -> 0 | G35: =IF(AND(E35>=6,E35<12),D35,0) -> 0 | H35: =IF(AND(E35>=12,E35<24),D35,0) -> 2299946400 | I35: =IF(AND(E35>=24,E35<36),D35,0) -> 0 | J35: =IF(E35>=36,D35,0) -> 0 | K35: =F35*$F$4+G35*$G$4+H35*$H$4+I35*$I$4+J35*$J$4 -> 1149973200
A36: Phải thu - Công ty Cổ Phần Trần Đức | B36: 0000564 | C36: 44119 | D36: 503591716 | E36: =($C$1-C36)/30 -> 2.5666667 | F36: =IF(E36<6,D36,0) -> 503591716 | G36: =IF(AND(E36>=6,E36<12),D36,0) -> 0 | H36: =IF(AND(E36>=12,E36<24),D36,0) -> 0 | I36: =IF(AND(E36>=24,E36<36),D36,0) -> 0 | J36: =IF(E36>=36,D36,0) -> 0 | K36: =F36*$F$4+G36*$G$4+H36*$H$4+I36*$I$4+J36*$J$4 -> 0
A37: Phải thu - Công ty Cổ Phần Trần Đức | B37: 0000568 | C37: 44130 | D37: 346001630 | E37: =($C$1-C37)/30 -> 2.2 | F37: =IF(E37<6,D37,0) -> 346001630 | G37: =IF(AND(E37>=6,E37<12),D37,0) -> 0 | H37: =IF(AND(E37>=12,E37<24),D37,0) -> 0 | I37: =IF(AND(E37>=24,E37<36),D37,0) -> 0 | J37: =IF(E37>=36,D37,0) -> 0 | K37: =F37*$F$4+G37*$G$4+H37*$H$4+I37*$I$4+J37*$J$4 -> 0
A38: Phải thu - Công ty Cổ Phần Trần Đức | B38: 0000568 | C38: 44130 | D38: 34600163 | E38: =($C$1-C38)/30 -> 2.2 | F38: =IF(E38<6,D38,0) -> 34600163 | G38: =IF(AND(E38>=6,E38<12),D38,0) -> 0 | H38: =IF(AND(E38>=12,E38<24),D38,0) -> 0 | I38: =IF(AND(E38>=24,E38<36),D38,0) -> 0 | J38: =IF(E38>=36,D38,0) -> 0 | K38: =F38*$F$4+G38*$G$4+H38*$H$4+I38*$I$4+J38*$J$4 -> 0
A39: Phải thu - Công ty Cổ Phần Trần Đức | B39: 0000009 | C39: 44160 | D39: 21292050 | E39: =($C$1-C39)/30 -> 1.2 | F39: =IF(E39<6,D39,0) -> 21292050 | G39: =IF(AND(E39>=6,E39<12),D39,0) -> 0 | H39: =IF(AND(E39>=12,E39<24),D39,0) -> 0 | I39: =IF(AND(E39>=24,E39<36),D39,0) -> 0 | J39: =IF(E39>=36,D39,0) -> 0 | K39: =F39*$F$4+G39*$G$4+H39*$H$4+I39*$I$4+J39*$J$4 -> 0
A40: Phải thu - Công ty Cổ Phần Trần Đức | B40: 0000009 | C40: 44160 | D40: 2129205 | E40: =($C$1-C40)/30 -> 1.2 | F40: =IF(E40<6,D40,0) -> 2129205 | G40: =IF(AND(E40>=6,E40<12),D40,0) -> 0 | H40: =IF(AND(E40>=12,E40<24),D40,0) -> 0 | I40: =IF(AND(E40>=24,E40<36),D40,0) -> 0 | J40: =IF(E40>=36,D40,0) -> 0 | K40: =F40*$F$4+G40*$G$4+H40*$H$4+I40*$I$4+J40*$J$4 -> 0
A41: Phải thu - Công ty Cổ Phần Trần Đức | B41: 0000053 | C41: 44193 | D41: 178183170 | E41: =($C$1-C41)/30 -> 0.1 | F41: =IF(E41<6,D41,0) -> 178183170 | G41: =IF(AND(E41>=6,E41<12),D41,0) -> 0 | H41: =IF(AND(E41>=12,E41<24),D41,0) -> 0 | I41: =IF(AND(E41>=24,E41<36),D41,0) -> 0 | J41: =IF(E41>=36,D41,0) -> 0 | K41: =F41*$F$4+G41*$G$4+H41*$H$4+I41*$I$4+J41*$J$4 -> 0
A42: Phải thu - Công ty Cổ Phần Trần Đức | B42: 0000053 | C42: 44193 | D42: 17818317 | E42: =($C$1-C42)/30 -> 0.1 | F42: =IF(E42<6,D42,0) -> 17818317 | G42: =IF(AND(E42>=6,E42<12),D42,0) -> 0 | H42: =IF(AND(E42>=12,E42<24),D42,0) -> 0 | I42: =IF(AND(E42>=24,E42<36),D42,0) -> 0 | J42: =IF(E42>=36,D42,0) -> 0 | K42: =F42*$F$4+G42*$G$4+H42*$H$4+I42*$I$4+J42*$J$4 -> 0
A43: Phải thu - Công Ty TNHH Thâm Vương | B43: 328 | C43: 43900 | D43: 620000000 | E43: =($C$1-C43)/30 -> 9.8666667 | F43: =IF(E43<6,D43,0) -> 0 | G43: =IF(AND(E43>=6,E43<12),D43,0) -> 620000000 | H43: =IF(AND(E43>=12,E43<24),D43,0) -> 0 | I43: =IF(AND(E43>=24,E43<36),D43,0) -> 0 | J43: =IF(E43>=36,D43,0) -> 0 | K43: =F43*$F$4+G43*$G$4+H43*$H$4+I43*$I$4+J43*$J$4 -> 186000000
A44: Phải thu - Công Ty TNHH Thâm Vương | B44: 328 | C44: 43900 | D44: 62000000 | E44: =($C$1-C44)/30 -> 9.8666667 | F44: =IF(E44<6,D44,0) -> 0 | G44: =IF(AND(E44>=6,E44<12),D44,0) -> 62000000 | H44: =IF(AND(E44>=12,E44<24),D44,0) -> 0 | I44: =IF(AND(E44>=24,E44<36),D44,0) -> 0 | J44: =IF(E44>=36,D44,0) -> 0 | K44: =F44*$F$4+G44*$G$4+H44*$H$4+I44*$I$4+J44*$J$4 -> 18600000
A45: Công Ty TNHH Eslite Home | B45: 0000040 | C45: 44166 | D45: 218208891 | E45: =($C$1-C45)/30 -> 1 | F45: =IF(E45<6,D45,0) -> 218208891 | G45: =IF(AND(E45>=6,E45<12),D45,0) -> 0 | H45: =IF(AND(E45>=12,E45<24),D45,0) -> 0 | I45: =IF(AND(E45>=24,E45<36),D45,0) -> 0 | J45: =IF(E45>=36,D45,0) -> 0 | K45: =F45*$F$4+G45*$G$4+H45*$H$4+I45*$I$4+J45*$J$4 -> 0
A46: Công Ty TNHH Eslite Home | B46: 0000040 | C46: 44166 | D46: 21820889 | E46: =($C$1-C46)/30 -> 1 | F46: =IF(E46<6,D46,0) -> 21820889 | G46: =IF(AND(E46>=6,E46<12),D46,0) -> 0 | H46: =IF(AND(E46>=12,E46<24),D46,0) -> 0 | I46: =IF(AND(E46>=24,E46<36),D46,0) -> 0 | J46: =IF(E46>=36,D46,0) -> 0 | K46: =F46*$F$4+G46*$G$4+H46*$H$4+I46*$I$4+J46*$J$4 -> 0
A47: Công Ty TNHH Eslite Home | B47: 0000074 | C47: 44195 | D47: 292016109 | E47: =($C$1-C47)/30 -> 0.033333333 | F47: =IF(E47<6,D47,0) -> 292016109 | G47: =IF(AND(E47>=6,E47<12),D47,0) -> 0 | H47: =IF(AND(E47>=12,E47<24),D47,0) -> 0 | I47: =IF(AND(E47>=24,E47<36),D47,0) -> 0 | J47: =IF(E47>=36,D47,0) -> 0 | K47: =F47*$F$4+G47*$G$4+H47*$H$4+I47*$I$4+J47*$J$4 -> 0
... A70: Phải thu - Công ty TNHH Bắc Hoằng | B70: 0000018 | C70: 44161 | D70: 43159628 | E70: =($C$1-C70)/30 -> 1.1666667 | F70: =IF(E70<6,D70,0) -> 43159628 | G70: =IF(AND(E70>=6,E70<12),D70,0) -> 0 | H70: =IF(AND(E70>=12,E70<24),D70,0) -> 0 | I70: =IF(AND(E70>=24,E70<36),D70,0) -> 0 | J70: =IF(E70>=36,D70,0) -> 0 | K70: =F70*$F$4+G70*$G$4+H70*$H$4+I70*$I$4+J70*$J$4 -> 0
A71: Phải thu - Cty TNHH Đức Thiện | C71: 43101 | D71: 392279594 | E71: =($C$1-C71)/30 -> 36.5 | F71: =IF(E71<6,D71,0) -> 0 | G71: =IF(AND(E71>=6,E71<12),D71,0) -> 0 | H71: =IF(AND(E71>=12,E71<24),D71,0) -> 0 | I71: =IF(AND(E71>=24,E71<36),D71,0) -> 0 | J71: =IF(E71>=36,D71,0) -> 392279594 | K71: =F71*$F$4+G71*$G$4+H71*$H$4+I71*$I$4+J71*$J$4 -> 392279594
A72: Phải thu - Công Ty TNHH Một Thành Viên Thắng Lâm | B72: 0000942 | C72: 43613 | D72: 294349044 | E72: =($C$1-C72)/30 -> 19.433333 | F72: =IF(E72<6,D72,0) -> 0 | G72: =IF(AND(E72>=6,E72<12),D72,0) -> 0 | H72: =IF(AND(E72>=12,E72<24),D72,0) -> 294349044 | I72: =IF(AND(E72>=24,E72<36),D72,0) -> 0 | J72: =IF(E72>=36,D72,0) -> 0 | K72: =F72*$F$4+G72*$G$4+H72*$H$4+I72*$I$4+J72*$J$4 -> 147174522
A73: Phải thu - Công Ty TNHH Một Thành Viên Thắng Lâm | B73: 0000942 | C73: 43613 | D73: 29434904 | E73: =($C$1-C73)/30 -> 19.433333 | F73: =IF(E73<6,D73,0) -> 0 | G73: =IF(AND(E73>=6,E73<12),D73,0) -> 0 | H73: =IF(AND(E73>=12,E73<24),D73,0) -> 29434904 | I73: =IF(AND(E73>=24,E73<36),D73,0) -> 0 | J73: =IF(E73>=36,D73,0) -> 0 | K73: =F73*$F$4+G73*$G$4+H73*$H$4+I73*$I$4+J73*$J$4 -> 14717452
A74: Phải thu - Công Ty TNHH Một Thành Viên Thắng Lâm | B74: 6 | C74: 43645 | D74: 57500000 | E74: =($C$1-C74)/30 -> 18.366667 | F74: =IF(E74<6,D74,0) -> 0 | G74: =IF(AND(E74>=6,E74<12),D74,0) -> 0 | H74: =IF(AND(E74>=12,E74<24),D74,0) -> 57500000 | I74: =IF(AND(E74>=24,E74<36),D74,0) -> 0 | J74: =IF(E74>=36,D74,0) -> 0 | K74: =F74*$F$4+G74*$G$4+H74*$H$4+I74*$I$4+J74*$J$4 -> 28750000
A75: Phải thu - Công Ty TNHH Một Thành Viên Thắng Lâm | B75: 6 | C75: 43645 | D75: 5750000 | E75: =($C$1-C75)/30 -> 18.366667 | F75: =IF(E75<6,D75,0) -> 0 | G75: =IF(AND(E75>=6,E75<12),D75,0) -> 0 | H75: =IF(AND(E75>=12,E75<24),D75,0) -> 5750000 | I75: =IF(AND(E75>=24,E75<36),D75,0) -> 0 | J75: =IF(E75>=36,D75,0) -> 0 | K75: =F75*$F$4+G75*$G$4+H75*$H$4+I75*$I$4+J75*$J$4 -> 2875000
A76: Phải thu - Công ty TNHH gỗ Hằng Nghĩa | B76: 0000062 | C76: 44194 | D76: 117307906 | E76: =($C$1-C76)/30 -> 0.066666667 | F76: =IF(E76<6,D76,0) -> 117307906 | G76: =IF(AND(E76>=6,E76<12),D76,0) -> 0 | H76: =IF(AND(E76>=12,E76<24),D76,0) -> 0 | I76: =IF(AND(E76>=24,E76<36),D76,0) -> 0 | J76: =IF(E76>=36,D76,0) -> 0 | K76: =F76*$F$4+G76*$G$4+H76*$H$4+I76*$I$4+J76*$J$4 -> 0
A77: Phải thu - Công ty TNHH gỗ Hằng Nghĩa | B77: 0000062 | C77: 44194 | D77: 11730791 | E77: =($C$1-C77)/30 -> 0.066666667 | F77: =IF(E77<6,D77,0) -> 11730791 | G77: =IF(AND(E77>=6,E77<12),D77,0) -> 0 | H77: =IF(AND(E77>=12,E77<24),D77,0) -> 0 | I77: =IF(AND(E77>=24,E77<36),D77,0) -> 0 | J77: =IF(E77>=36,D77,0) -> 0 | K77: =F77*$F$4+G77*$G$4+H77*$H$4+I77*$I$4+J77*$J$4 -> 0
A78: Phải thu - Công ty TNHH gỗ Hằng Nghĩa | B78: 0000069 | C78: 44195 | D78: 182018087 | E78: =($C$1-C78)/30 -> 0.033333333 | F78: =IF(E78<6,D78,0) -> 182018087 | G78: =IF(AND(E78>=6,E78<12),D78,0) -> 0 | H78: =IF(AND(E78>=12,E78<24),D78,0) -> 0 | I78: =IF(AND(E78>=24,E78<36),D78,0) -> 0 | J78: =IF(E78>=36,D78,0) -> 0 | K78: =F78*$F$4+G78*$G$4+H78*$H$4+I78*$I$4+J78*$J$4 -> 0
A79: Phải thu - Công ty TNHH gỗ Hằng Nghĩa | B79: 0000069 | C79: 44195 | D79: 18201809 | E79: =($C$1-C79)/30 -> 0.033333333 | F79: =IF(E79<6,D79,0) -> 18201809 | G79: =IF(AND(E79>=6,E79<12),D79,0) -> 0 | H79: =IF(AND(E79>=12,E79<24),D79,0) -> 0 | I79: =IF(AND(E79>=24,E79<36),D79,0) -> 0 | J79: =IF(E79>=36,D79,0) -> 0 | K79: =F79*$F$4+G79*$G$4+H79*$H$4+I79*$I$4+J79*$J$4 -> 0
A80: Phải thu- Công Ty TNHH Mori Shige | B80: 0000021 | C80: 44162 | D80: 125834703 | E80: =($C$1-C80)/30 -> 1.1333333 | F80: =IF(E80<6,D80,0) -> 125834703 | G80: =IF(AND(E80>=6,E80<12),D80,0) -> 0 | H80: =IF(AND(E80>=12,E80<24),D80,0) -> 0 | I80: =IF(AND(E80>=24,E80<36),D80,0) -> 0 | J80: =IF(E80>=36,D80,0) -> 0 | K80: =F80*$F$4+G80*$G$4+H80*$H$4+I80*$I$4+J80*$J$4 -> 0
A81: Phải thu- Công Ty TNHH Mori Shige | B81: 0000021 | C81: 44162 | D81: 12583470 | E81: =($C$1-C81)/30 -> 1.1333333 | F81: =IF(E81<6,D81,0) -> 12583470 | G81: =IF(AND(E81>=6,E81<12),D81,0) -> 0 | H81: =IF(AND(E81>=12,E81<24),D81,0) -> 0 | I81: =IF(AND(E81>=24,E81<36),D81,0) -> 0 | J81: =IF(E81>=36,D81,0) -> 0 | K81: =F81*$F$4+G81*$G$4+H81*$H$4+I81*$I$4+J81*$J$4 -> 0
A82: Phải thu- Công Ty TNHH Mori Shige | B82: 0000070 | C82: 44195 | D82: 131148300 | E82: =($C$1-C82)/30 -> 0.033333333 | F82: =IF(E82<6,D82,0) -> 131148300 | G82: =IF(AND(E82>=6,E82<12),D82,0) -> 0 | H82: =IF(AND(E82>=12,E82<24),D82,0) -> 0 | I82: =IF(AND(E82>=24,E82<36),D82,0) -> 0 | J82: =IF(E82>=36,D82,0) -> 0 | K82: =F82*$F$4+G82*$G$4+H82*$H$4+I82*$I$4+J82*$J$4 -> 0
A83: Phải thu- Công Ty TNHH Mori Shige | B83: 0000070 | C83: 44195 | D83: 13114830 | E83: =($C$1-C83)/30 -> 0.033333333 | F83: =IF(E83<6,D83,0) -> 13114830 | G83: =IF(AND(E83>=6,E83<12),D83,0) -> 0 | H83: =IF(AND(E83>=12,E83<24),D83,0) -> 0 | I83: =IF(AND(E83>=24,E83<36),D83,0) -> 0 | J83: =IF(E83>=36,D83,0) -> 0 | K83: =F83*$F$4+G83*$G$4+H83*$H$4+I83*$I$4+J83*$J$4 -> 0
A84: Phải thu - Cty TNHH Thành Phú Phát | B84: 0000067 | C84: 44194 | D84: 1367660 | E84: =($C$1-C84)/30 -> 0.066666667 | F84: =IF(E84<6,D84,0) -> 1367660 | G84: =IF(AND(E84>=6,E84<12),D84,0) -> 0 | H84: =IF(AND(E84>=12,E84<24),D84,0) -> 0 | I84: =IF(AND(E84>=24,E84<36),D84,0) -> 0 | J84: =IF(E84>=36,D84,0) -> 0 | K84: =F84*$F$4+G84*$G$4+H84*$H$4+I84*$I$4+J84*$J$4 -> 0
A85: Phải thu - Cty TNHH Thành Phú Phát | B85: 0000067 | C85: 44194 | D85: 32775396 | E85: =($C$1-C85)/30 -> 0.066666667 | F85: =IF(E85<6,D85,0) -> 32775396 | G85: =IF(AND(E85>=6,E85<12),D85,0) -> 0 | H85: =IF(AND(E85>=12,E85<24),D85,0) -> 0 | I85: =IF(AND(E85>=24,E85<36),D85,0) -> 0 | J85: =IF(E85>=36,D85,0) -> 0 | K85: =F85*$F$4+G85*$G$4+H85*$H$4+I85*$I$4+J85*$J$4 -> 0
A86: Phải thu - Cty TNHH Thành Phú Phát | B86: 0000067 | C86: 44194 | D86: 3414306 | E86: =($C$1-C86)/30 -> 0.066666667 | F86: =IF(E86<6,D86,0) -> 3414306 | G86: =IF(AND(E86>=6,E86<12),D86,0) -> 0 | H86: =IF(AND(E86>=12,E86<24),D86,0) -> 0 | I86: =IF(AND(E86>=24,E86<36),D86,0) -> 0 | J86: =IF(E86>=36,D86,0) -> 0 | K86: =F86*$F$4+G86*$G$4+H86*$H$4+I86*$I$4+J86*$J$4 -> 0
A87: Phải thu - Cty TNHH Thành Phú Phát | B87: 0000068 | C87: 44195 | D87: 206128858 | E87: =($C$1-C87)/30 -> 0.033333333 | F87: =IF(E87<6,D87,0) -> 206128858 | G87: =IF(AND(E87>=6,E87<12),D87,0) -> 0 | H87: =IF(AND(E87>=12,E87<24),D87,0) -> 0 | I87: =IF(AND(E87>=24,E87<36),D87,0) -> 0 | J87: =IF(E87>=36,D87,0) -> 0 | K87: =F87*$F$4+G87*$G$4+H87*$H$4+I87*$I$4+J87*$J$4 -> 0
... A106: Phải thu - Công ty TNHH View Full Việt Nam | B106: 0000047 | C106: 44190 | D106: 6915568 | E106: =($C$1-C106)/30 -> 0.2 | F106: =IF(E106<6,D106,0) -> 6915568 | G106: =IF(AND(E106>=6,E106<12),D106,0) -> 0 | H106: =IF(AND(E106>=12,E106<24),D106,0) -> 0 | I106: =IF(AND(E106>=24,E106<36),D106,0) -> 0 | J106: =IF(E106>=36,D106,0) -> 0 | K106: =F106*$F$4+G106*$G$4+H106*$H$4+I106*$I$4+J106*$J$4 -> 0
A107: Phải thu - Công ty TNHH View Full Việt Nam | C107: 43101 | D107: 14910315 | E107: =($C$1-C107)/30 -> 36.5 | F107: =IF(E107<6,D107,0) -> 0 | G107: =IF(AND(E107>=6,E107<12),D107,0) -> 0 | H107: =IF(AND(E107>=12,E107<24),D107,0) -> 0 | I107: =IF(AND(E107>=24,E107<36),D107,0) -> 0 | J107: =IF(E107>=36,D107,0) -> 14910315 | K107: =F107*$F$4+G107*$G$4+H107*$H$4+I107*$I$4+J107*$J$4 -> 14910315
A108: Phải thu - Cty TNHH Kim Phong | B108: 0000059 | C108: 44194 | D108: 95793200 | E108: =($C$1-C108)/30 -> 0.066666667 | F108: =IF(E108<6,D108,0) -> 95793200 | G108: =IF(AND(E108>=6,E108<12),D108,0) -> 0 | H108: =IF(AND(E108>=12,E108<24),D108,0) -> 0 | I108: =IF(AND(E108>=24,E108<36),D108,0) -> 0 | J108: =IF(E108>=36,D108,0) -> 0 | K108: =F108*$F$4+G108*$G$4+H108*$H$4+I108*$I$4+J108*$J$4 -> 0
A109: Phải thu - Cty TNHH Kim Phong | B109: 0000059 | C109: 44194 | D109: 9579320 | E109: =($C$1-C109)/30 -> 0.066666667 | F109: =IF(E109<6,D109,0) -> 9579320 | G109: =IF(AND(E109>=6,E109<12),D109,0) -> 0 | H109: =IF(AND(E109>=12,E109<24),D109,0) -> 0 | I109: =IF(AND(E109>=24,E109<36),D109,0) -> 0 | J109: =IF(E109>=36,D109,0) -> 0 | K109: =F109*$F$4+G109*$G$4+H109*$H$4+I109*$I$4+J109*$J$4 -> 0
A110: Phải thu - Công ty TNHH nội thất gỗ Phú Đỉnh | B110: 275 | C110: 43845 | D110: 12449974 | E110: =($C$1-C110)/30 -> 11.7 | F110: =IF(E110<6,D110,0) -> 0 | G110: =IF(AND(E110>=6,E110<12),D110,0) -> 12449974 | H110: =IF(AND(E110>=12,E110<24),D110,0) -> 0 | I110: =IF(AND(E110>=24,E110<36),D110,0) -> 0 | J110: =IF(E110>=36,D110,0) -> 0 | K110: =F110*$F$4+G110*$G$4+H110*$H$4+I110*$I$4+J110*$J$4 -> 3734992.2
A111: Phải thu - Công ty TNHH nội thất gỗ Phú Đỉnh | B111: 275 | C111: 43845 | D111: 1244997 | E111: =($C$1-C111)/30 -> 11.7 | F111: =IF(E111<6,D111,0) -> 0 | G111: =IF(AND(E111>=6,E111<12),D111,0) -> 1244997 | H111: =IF(AND(E111>=12,E111<24),D111,0) -> 0 | I111: =IF(AND(E111>=24,E111<36),D111,0) -> 0 | J111: =IF(E111>=36,D111,0) -> 0 | K111: =F111*$F$4+G111*$G$4+H111*$H$4+I111*$I$4+J111*$J$4 -> 373499.1
A112: Phải thu - Công ty TNHH nội thất gỗ Phú Đỉnh | B112: 229 | C112: 43887 | D112: 0 | E112: =($C$1-C112)/30 -> 10.3 | F112: =IF(E112<6,D112,0) -> 0 | G112: =IF(AND(E112>=6,E112<12),D112,0) -> 0 | H112: =IF(AND(E112>=12,E112<24),D112,0) -> 0 | I112: =IF(AND(E112>=24,E112<36),D112,0) -> 0 | J112: =IF(E112>=36,D112,0) -> 0 | K112: =F112*$F$4+G112*$G$4+H112*$H$4+I112*$I$4+J112*$J$4 -> 0
A113: Phải thu - Công ty TNHH nội thất gỗ Phú Đỉnh | B113: 229 | C113: 43887 | D113: 0 | E113: =($C$1-C113)/30 -> 10.3 | F113: =IF(E113<6,D113,0) -> 0 | G113: =IF(AND(E113>=6,E113<12),D113,0) -> 0 | H113: =IF(AND(E113>=12,E113<24),D113,0) -> 0 | I113: =IF(AND(E113>=24,E113<36),D113,0) -> 0 | J113: =IF(E113>=36,D113,0) -> 0 | K113: =F113*$F$4+G113*$G$4+H113*$H$4+I113*$I$4+J113*$J$4 -> 0
A114: Phải thu - Công ty TNHH nội thất gỗ Phú Đỉnh | B114: 324 | C114: 43892 | D114: 2053500 | E114: =($C$1-C114)/30 -> 10.133333 | F114: =IF(E114<6,D114,0) -> 0 | G114: =IF(AND(E114>=6,E114<12),D114,0) -> 2053500 | H114: =IF(AND(E114>=12,E114<24),D114,0) -> 0 | I114: =IF(AND(E114>=24,E114<36),D114,0) -> 0 | J114: =IF(E114>=36,D114,0) -> 0 | K114: =F114*$F$4+G114*$G$4+H114*$H$4+I114*$I$4+J114*$J$4 -> 616050
A115: Phải thu - Công ty TNHH nội thất gỗ Phú Đỉnh | B115: 324 | C115: 43892 | D115: 205350 | E115: =($C$1-C115)/30 -> 10.133333 | F115: =IF(E115<6,D115,0) -> 0 | G115: =IF(AND(E115>=6,E115<12),D115,0) -> 205350 | H115: =IF(AND(E115>=12,E115<24),D115,0) -> 0 | I115: =IF(AND(E115>=24,E115<36),D115,0) -> 0 | J115: =IF(E115>=36,D115,0) -> 0 | K115: =F115*$F$4+G115*$G$4+H115*$H$4+I115*$I$4+J115*$J$4 -> 61605
A116: Phải thu - Công ty TNHH nội thất gỗ Phú Đỉnh | B116: 275 | C116: 43916 | D116: 0 | E116: =($C$1-C116)/30 -> 9.3333333 | F116: =IF(E116<6,D116,0) -> 0 | G116: =IF(AND(E116>=6,E116<12),D116,0) -> 0 | H116: =IF(AND(E116>=12,E116<24),D116,0) -> 0 | I116: =IF(AND(E116>=24,E116<36),D116,0) -> 0 | J116: =IF(E116>=36,D116,0) -> 0 | K116: =F116*$F$4+G116*$G$4+H116*$H$4+I116*$I$4+J116*$J$4 -> 0
A117: Phải thu - Công ty TNHH nội thất gỗ Phú Đỉnh | B117: 378 | C117: 43956 | D117: 8027980 | E117: =($C$1-C117)/30 -> 8 | F117: =IF(E117<6,D117,0) -> 0 | G117: =IF(AND(E117>=6,E117<12),D117,0) -> 8027980 | H117: =IF(AND(E117>=12,E117<24),D117,0) -> 0 | I117: =IF(AND(E117>=24,E117<36),D117,0) -> 0 | J117: =IF(E117>=36,D117,0) -> 0 | K117: =F117*$F$4+G117*$G$4+H117*$H$4+I117*$I$4+J117*$J$4 -> 2408394
A118: Phải thu - Công ty TNHH nội thất gỗ Phú Đỉnh | B118: 378 | C118: 43956 | D118: 802798 | E118: =($C$1-C118)/30 -> 8 | F118: =IF(E118<6,D118,0) -> 0 | G118: =IF(AND(E118>=6,E118<12),D118,0) -> 802798 | H118: =IF(AND(E118>=12,E118<24),D118,0) -> 0 | I118: =IF(AND(E118>=24,E118<36),D118,0) -> 0 | J118: =IF(E118>=36,D118,0) -> 0 | K118: =F118*$F$4+G118*$G$4+H118*$H$4+I118*$I$4+J118*$J$4 -> 240839.4
A119: Phải thu - Công ty TNHH nội thất gỗ Phú Đỉnh | B119: 324 | C119: 43979 | D119: 0 | E119: =($C$1-C119)/30 -> 7.2333333 | F119: =IF(E119<6,D119,0) -> 0 | G119: =IF(AND(E119>=6,E119<12),D119,0) -> 0 | H119: =IF(AND(E119>=12,E119<24),D119,0) -> 0 | I119: =IF(AND(E119>=24,E119<36),D119,0) -> 0 | J119: =IF(E119>=36,D119,0) -> 0 | K119: =F119*$F$4+G119*$G$4+H119*$H$4+I119*$I$4+J119*$J$4 -> 0
... A149: Công Ty TNHH MTV Lâm Dương | B149: 0000065 | C149: 44194 | D149: 1104480 | E149: =($C$1-C149)/30 -> 0.066666667 | F149: =IF(E149<6,D149,0) -> 1104480 | G149: =IF(AND(E149>=6,E149<12),D149,0) -> 0 | H149: =IF(AND(E149>=12,E149<24),D149,0) -> 0 | I149: =IF(AND(E149>=24,E149<36),D149,0) -> 0 | J149: =IF(E149>=36,D149,0) -> 0 | K149: =F149*$F$4+G149*$G$4+H149*$H$4+I149*$I$4+J149*$J$4 -> 0
A150: Công ty TNHH Sản xuất TM B H | B150: 966 | C150: 43620 | D150: 57601406 | E150: =($C$1-C150)/30 -> 19.2 | F150: =IF(E150<6,D150,0) -> 0 | G150: =IF(AND(E150>=6,E150<12),D150,0) -> 0 | H150: =IF(AND(E150>=12,E150<24),D150,0) -> 57601406 | I150: =IF(AND(E150>=24,E150<36),D150,0) -> 0 | J150: =IF(E150>=36,D150,0) -> 0 | K150: =F150*$F$4+G150*$G$4+H150*$H$4+I150*$I$4+J150*$J$4 -> 28800703
A151: Phải thu - Công ty TNHH Đồ Gỗ Gia Dụng Dinh Gia VN | B151: 0000034 | C151: 44165 | D151: 30668380 | E151: =($C$1-C151)/30 -> 1.0333333 | F151: =IF(E151<6,D151,0) -> 30668380 | G151: =IF(AND(E151>=6,E151<12),D151,0) -> 0 | H151: =IF(AND(E151>=12,E151<24),D151,0) -> 0 | I151: =IF(AND(E151>=24,E151<36),D151,0) -> 0 | J151: =IF(E151>=36,D151,0) -> 0 | K151: =F151*$F$4+G151*$G$4+H151*$H$4+I151*$I$4+J151*$J$4 -> 0
A152: Phải thu - Công ty TNHH Đồ Gỗ Gia Dụng Dinh Gia VN | B152: 0000034 | C152: 44165 | D152: 3066838 | E152: =($C$1-C152)/30 -> 1.0333333 | F152: =IF(E152<6,D152,0) -> 3066838 | G152: =IF(AND(E152>=6,E152<12),D152,0) -> 0 | H152: =IF(AND(E152>=12,E152<24),D152,0) -> 0 | I152: =IF(AND(E152>=24,E152<36),D152,0) -> 0 | J152: =IF(E152>=36,D152,0) -> 0 | K152: =F152*$F$4+G152*$G$4+H152*$H$4+I152*$I$4+J152*$J$4 -> 0
A153: Phải thu - Công ty TNHH Đồ Gỗ Gia Dụng Dinh Gia VN | B153: 0000055 | C153: 44193 | D153: 18988200 | E153: =($C$1-C153)/30 -> 0.1 | F153: =IF(E153<6,D153,0) -> 18988200 | G153: =IF(AND(E153>=6,E153<12),D153,0) -> 0 | H153: =IF(AND(E153>=12,E153<24),D153,0) -> 0 | I153: =IF(AND(E153>=24,E153<36),D153,0) -> 0 | J153: =IF(E153>=36,D153,0) -> 0 | K153: =F153*$F$4+G153*$G$4+H153*$H$4+I153*$I$4+J153*$J$4 -> 0
A154: Phải thu - Công ty TNHH Đồ Gỗ Gia Dụng Dinh Gia VN | B154: 0000055 | C154: 44193 | D154: 1898820 | E154: =($C$1-C154)/30 -> 0.1 | F154: =IF(E154<6,D154,0) -> 1898820 | G154: =IF(AND(E154>=6,E154<12),D154,0) -> 0 | H154: =IF(AND(E154>=12,E154<24),D154,0) -> 0 | I154: =IF(AND(E154>=24,E154<36),D154,0) -> 0 | J154: =IF(E154>=36,D154,0) -> 0 | K154: =F154*$F$4+G154*$G$4+H154*$H$4+I154*$I$4+J154*$J$4 -> 0
A155: Phải thu - Cty TNHH Wan Li Hang (Việt Nam) | B155: 0000011 | C155: 44160 | D155: 18933600 | E155: =($C$1-C155)/30 -> 1.2 | F155: =IF(E155<6,D155,0) -> 18933600 | G155: =IF(AND(E155>=6,E155<12),D155,0) -> 0 | H155: =IF(AND(E155>=12,E155<24),D155,0) -> 0 | I155: =IF(AND(E155>=24,E155<36),D155,0) -> 0 | J155: =IF(E155>=36,D155,0) -> 0 | K155: =F155*$F$4+G155*$G$4+H155*$H$4+I155*$I$4+J155*$J$4 -> 0
A156: Phải thu - Cty TNHH Wan Li Hang (Việt Nam) | B156: 0000011 | C156: 44160 | D156: 1893360 | E156: =($C$1-C156)/30 -> 1.2 | F156: =IF(E156<6,D156,0) -> 1893360 | G156: =IF(AND(E156>=6,E156<12),D156,0) -> 0 | H156: =IF(AND(E156>=12,E156<24),D156,0) -> 0 | I156: =IF(AND(E156>=24,E156<36),D156,0) -> 0 | J156: =IF(E156>=36,D156,0) -> 0 | K156: =F156*$F$4+G156*$G$4+H156*$H$4+I156*$I$4+J156*$J$4 -> 0
A157: Phải thu - Cty TNHH Wan Li Hang (Việt Nam) | B157: 0000058 | C157: 44194 | D157: 18547200 | E157: =($C$1-C157)/30 -> 0.066666667 | F157: =IF(E157<6,D157,0) -> 18547200 | G157: =IF(AND(E157>=6,E157<12),D157,0) -> 0 | H157: =IF(AND(E157>=12,E157<24),D157,0) -> 0 | I157: =IF(AND(E157>=24,E157<36),D157,0) -> 0 | J157: =IF(E157>=36,D157,0) -> 0 | K157: =F157*$F$4+G157*$G$4+H157*$H$4+I157*$I$4+J157*$J$4 -> 0
A158: Phải thu - Cty TNHH Wan Li Hang (Việt Nam) | B158: 0000058 | C158: 44194 | D158: 1854720 | E158: =($C$1-C158)/30 -> 0.066666667 | F158: =IF(E158<6,D158,0) -> 1854720 | G158: =IF(AND(E158>=6,E158<12),D158,0) -> 0 | H158: =IF(AND(E158>=12,E158<24),D158,0) -> 0 | I158: =IF(AND(E158>=24,E158<36),D158,0) -> 0 | J158: =IF(E158>=36,D158,0) -> 0 | K158: =F158*$F$4+G158*$G$4+H158*$H$4+I158*$I$4+J158*$J$4 -> 0
A159: Phải thu - Công ty TNHH Long Hao | B159: 0000571 | C159: 44130 | D159: 6911615 | E159: =($C$1-C159)/30 -> 2.2 | F159: =IF(E159<6,D159,0) -> 6911615 | G159: =IF(AND(E159>=6,E159<12),D159,0) -> 0 | H159: =IF(AND(E159>=12,E159<24),D159,0) -> 0 | I159: =IF(AND(E159>=24,E159<36),D159,0) -> 0 | J159: =IF(E159>=36,D159,0) -> 0 | K159: =F159*$F$4+G159*$G$4+H159*$H$4+I159*$I$4+J159*$J$4 -> 0
A160: Phải thu - Công ty TNHH Long Hao | B160: 0000571 | C160: 44130 | D160: 691162 | E160: =($C$1-C160)/30 -> 2.2 | F160: =IF(E160<6,D160,0) -> 691162 | G160: =IF(AND(E160>=6,E160<12),D160,0) -> 0 | H160: =IF(AND(E160>=12,E160<24),D160,0) -> 0 | I160: =IF(AND(E160>=24,E160<36),D160,0) -> 0 | J160: =IF(E160>=36,D160,0) -> 0 | K160: =F160*$F$4+G160*$G$4+H160*$H$4+I160*$I$4+J160*$J$4 -> 0
A161: Phải thu - Công ty TNHH Long Hao | B161: 0000005 | C161: 44160 | D161: 15145500 | E161: =($C$1-C161)/30 -> 1.2 | F161: =IF(E161<6,D161,0) -> 15145500 | G161: =IF(AND(E161>=6,E161<12),D161,0) -> 0 | H161: =IF(AND(E161>=12,E161<24),D161,0) -> 0 | I161: =IF(AND(E161>=24,E161<36),D161,0) -> 0 | J161: =IF(E161>=36,D161,0) -> 0 | K161: =F161*$F$4+G161*$G$4+H161*$H$4+I161*$I$4+J161*$J$4 -> 0
A162: Phải thu - Công ty TNHH Long Hao | B162: 0000005 | C162: 44160 | D162: 1514550 | E162: =($C$1-C162)/30 -> 1.2 | F162: =IF(E162<6,D162,0) -> 1514550 | G162: =IF(AND(E162>=6,E162<12),D162,0) -> 0 | H162: =IF(AND(E162>=12,E162<24),D162,0) -> 0 | I162: =IF(AND(E162>=24,E162<36),D162,0) -> 0 | J162: =IF(E162>=36,D162,0) -> 0 | K162: =F162*$F$4+G162*$G$4+H162*$H$4+I162*$I$4+J162*$J$4 -> 0
... A211: Phải thu - Công ty CP SX kinh doanh XNK Minh Tiến | B211: 0000030 | C211: 44163 | D211: 2176680 | E211: =($C$1-C211)/30 -> 1.1 | F211: =IF(E211<6,D211,0) -> 2176680 | G211: =IF(AND(E211>=6,E211<12),D211,0) -> 0 | H211: =IF(AND(E211>=12,E211<24),D211,0) -> 0 | I211: =IF(AND(E211>=24,E211<36),D211,0) -> 0 | J211: =IF(E211>=36,D211,0) -> 0 | K211: =F211*$F$4+G211*$G$4+H211*$H$4+I211*$I$4+J211*$J$4 -> 0
A214: NỢ XẤU VÀ NỢ KHÓ ĐÒI
C215: 44561 | G215: 44196 | J215: 2022
B216: Số ngày quá hạn | C216: Giá gốc | D216: Giá trị có thể thu hồi | F216: Số ngày quá hạn | G216: Giá gốc | H216: Giá trị có thể thu hồi
A217: Nợ quá hạn
A218: Công ty TNHH Sản xuất TM B H | B218: 02 - 03 năm | C218: 57601406 | D218: 17280422 | F218: 01 - 02 năm | G218: 57601406 | H218: 28800703 | J218: 57601406 | K218: =+J218-C218 -> 0 | L218: công nợ 2019
A219: Công Ty TNHH TM Tam Hợp Phát | B219: 02 - 03 năm | C219: 1699946400 | D219: 509983920 | F219: 01 - 02 năm | G219: 2299946400 | H219: 1149973200 | J219: 1699946400 | K219: =+J219-C219 -> 0 | L219: dư nợ chưa thanh tón hết
...

Sheet CN
A1: 42947 | B1: 0000188 | C1: Poly trang trí - Công ty TNHH nội thất gỗ Phú Đỉnh | D1: 5111 | E1: 19213770 | G1: treo nợ
A2: 42947 | B2: 0000188 | C2: VAT đầu ra - Công ty TNHH nội thất gỗ Phú Đỉnh | D2: 33311 | E2: 1921377 | F2: =+E2+E1 -> 21135147
A3: 43069 | B3: 0 | C3: Phải thu - Công ty TNHH nội thất gỗ Phú Đỉnh | D3: 1121IVB | E3: 0 | F3: 11498772 | G3: =+E1+E2-F3 -> 9636375
G4: 55618.5 | H4: thiếu phí TT | I4: hd 313 10/2017
A5: 415 | B5: 43130 | C5: Poly trang trí - Công ty TNHH nội thất gỗ Phú Đỉnh | D5: 5111 | E5: 27421380 | G5: =+E5+E6 -> 30163518
A6: 415 | B6: 43130 | C6: VAT đầu ra - Công ty TNHH nội thất gỗ Phú Đỉnh | D6: 33311 | E6: 2742138
G7: 53394 | H7: thiếu phí TT | I7: hd 378 5/5/20
G8: 53399 | H8: thiếu phí TT | I8: hd 24/08/20
G10: =+G4+G7+G8 -> 162411.5
B11: 0000077 | C11: DT Bán poly-HD 77-18/01/21-Cty Phú Đỉnh | D11: 5112 | E11: 3575520 | F11: =+E11+E12 -> 3933072 | G11: =+F11 -> 3933072
B12: 0000077 | C12: Thuế GTGT đầu ra HĐ: 0000077,18/01/21 | D12: 33311 | E12: 357552
G13: =+G11+G5+G3 -> 43732965
A16: 42947 | B16: 0000188 | C16: Poly trang trí - Công ty TNHH nội thất gỗ Phú Đỉnh | D16: 5111 | E16: 19213770 | G16: treo nợ đến hiện tại
A17: 42947 | B17: 0000188 | C17: VAT đầu ra - Công ty TNHH nội thất gỗ Phú Đỉnh | D17: 33311 | E17: 1921377 | F17: =+E17+E16 -> 21135147
A18: 43069 | B18: 0 | C18: Phải thu - Công ty TNHH nội thất gỗ Phú Đỉnh | D18: 1121IVB | E18: 0 | F18: 11498772 | G18: =+E16+E17-F18 -> 9636375
A20: 415 | B20: 43130 | C20: Poly trang trí - Công ty TNHH nội thất gỗ Phú Đỉnh | D20: 5111 | E20: 27421380 | G20: =+E20+E21 -> 30163518
A21: 415 | B21: 43130 | C21: VAT đầu ra - Công ty TNHH nội thất gỗ Phú Đỉnh | D21: 33311 | E21: 2742138 | H21: 39799893
B23: 0000077 | C23: DT Bán poly-HD 77-18/01/21-Cty Phú Đỉnh | D23: 5112 | E23: 3575520 | F23: =+E23+E24 -> 3933072 | G23: =+F23 -> 3933072
B24: 0000077 | C24: Thuế GTGT đầu ra HĐ: 0000077,18/01/21 | D24: 33311 | E24: 357552 | G24: =SUM(G18:G23) -> 43732965
A28: 70 | B28: 44722 | C28: Chi phí Dầu DO, Xăng Ron E5-HĐ 70-10/06/22-CTY An Khánh Phát | D28: 6417 | G28: 7293236
A29: 70 | B29: 44722 | C29: Chi phí Dầu DO, Xăng Ron E5-HĐ 70-10/06/22-CTY An Khánh Phát | D29: 6427 | G29: 1099273
A30: 70 | B30: 44722 | C30: Thuế GTGT mua vào HĐ số :70,10/06/22 | D30: 1331 | G30: 839251
G31: =SUM(G28:G30) -> 9231760
C34: Diễn giải | D34: TK | E34: VND
A35: Ngày | B35: Số Hđ | D35: DU | E35: Nợ | F35: Có
C36: SỐ DƯ ĐẦU KỲ | D36: 0 | E36: 519590653 | F36: 0
A37: 44222 | B37: 0000085 | C37: DT Bán poly-HD 85-26/01/21-Cty Siêu Nghệ | D37: 5112 | E37: 221116661 | F37: 0
A38: 44222 | B38: 0000085 | C38: Thuế GTGT đầu ra HĐ: 0000085,26/01/21 | D38: 33311 | E38: 22111666 | F38: 0
A39: 44231 | B39: 0000585 | C39: Cty Siêu Nghệ thanh toán tiền HD 585 | D39: 1121IVB | E39: 0 | F39: 72677671
A40: 44254 | B40: 0000127 | C40: DT Bán poly HD 127-27/02/21-Cty Siêu NGhệ | D40: 5112 | E40: 131162922 | F40: 0
A41: 44254 | B41: 0000127 | C41: Thuế GTGT đầu ra HĐ: 0000127,27/02/21 | D41: 33311 | E41: 13116292 | F41: 0
A42: 44267 | B42: 0000033 | C42: Công Ty Siêu Nghệ thanh toán tiền 1 phần HĐ 33 | D42: 1121IVB | E42: 0 | F42: 99972500
A43: 44286 | B43: 0000161 | C43: DT Bán poly trang trí HĐ 161-31/03/21-Cty Siêu Nghệ | D43: 5112 | E43: 279488246 | F43: 0
A44: 44286 | B44: 0000161 | C44: Thuế GTGT đầu ra HĐ: 0000161,31/03/21 | D44: 33311 | E44: 27948825 | F44: 0 | I44: =+E40+E41+E43+E44 -> 451716285 | J44: 300000000 | K44: =+I44-J44 -> 151716285 | L44: 127+161 | M44: 44589 | N44: CTY Siêu Nghệ thanh toán tiền hàng T2+1 phần T3/21-HĐ 127+161
A45: 44287 | C45: Công Ty Siêu Nghệ Thanh toán phần còn lại hóa đơn 33 và 1 phần hóa đơn 66/t12 2020 | D45: 1121IVB | E45: 0 | F45: 175000000
A46: 44306 | B46: 33+66 | C46: Công Ty Siêu Nghệ Thanh Toán Tiền HĐ 33+66 | D46: 1121IVB | E46: 0 | F46: 171912982
A47: 44306 | C47: Phí ngân hàng | D47: 6427 | E47: 0 | F47: 27500
A48: 44315 | B48: 0000187 | C48: DT Bán poly trang trí HĐ 187-29/04/21-Cty Siêu NGhệ | D48: 5112 | E48: 295822872 | F48: 0
A49: 44315 | B49: 0000187 | C49: Thuế GTGT đầu ra HĐ: 0000187,29/04/21 | D49: 33311 | E49: 29582287 | F49: 0 | I49: =+K44+E48+E49 -> 477121444 | J49: 200000000 | K49: =+I49-J49 -> 277121444 | L49: 161+187 | M49: 44677 | N49: DT Bán poly trang trí HĐ 161(31/03/21)+187(29/04/21)-CTY Siêu Nghệ
I50: =+K49 -> 277121444 | J50: 50000000 | K50: =+I50-J50 -> 227121444 | L50: 187 | M50: 44869 | N50: CTYTNHH SIÊU NGHỆ thanh tiếp 1 phần tiền hàng T4/21 HD 187 (29/04/21)
A51: 44344 | B51: 0000224 | C51: DT Bán poly trang trí HĐ 224-28/05/21-Cty Siêu NGhệ | D51: 5112 | E51: 384118906 | F51: 0
A52: 44344 | B52: 0000224 | C52: Thuế GTGT đầu ra HĐ: 0000224,28/05/21 | D52: 33311 | E52: 38411891 | F52: 0
A53: 44349 | B53: 0000085 | C53: Công Ty Siêu NGhệ thanh toán tiền HĐ 85 | D53: 1121IVB | E53: 0 | F53: 243228327
A54: 44377 | B54: 0000260 | C54: DT Bán poly trang trí HĐ 260-30/06/21-Cty Siêu Nghệ | D54: 5112 | E54: 78597838 | F54: 0
A55: 44377 | B55: 0000260 | C55: Thuế GTGT đầu ra HĐ: 0000260,30/06/21 | D55: 33311 | E55: 7859784 | F55: 0
A56: 44435 | B56: 0000281 | C56: DT Bán Poly trang trí-HĐ 281-27/08/21-Cty Siêu Nghệ | D56: 5112 | E56: 12399205 | F56: 0
A57: 44435 | B57: 0000281 | C57: Thuế GTGT đầu ra HĐ: 0000281,27/08/21 | D57: 33311 | E57: 1239921 | F57: 0
C58: CỘNG PHÁT SINH | E58: 1542977316 | F58: 762818980
C59: SỐ DƯ CUỐI KỲ | E59: 1299748989 | F59: 0
K60: =+K50+SUM(E51:E57) -> 749748989
A61: 104 | B61: 44837 | C61: DT Bán Poly trang trí - HD104 -CTY TNHH MTV SIÊU NGHỆ | D61: 5112 | E61: 113749650
A62: 104 | B62: 44837 | C62: Thuế GTGT đầu ra HĐ: 104,03/10/22 | D62: 33311 | E62: 9099972
E63: =SUM(E61:E62) -> 122849622 | K63: =+K60+E63 -> 872598611
A68: 44166 | B68: 0000040 | C68: DT Bán poly trang trí-HD 40-01/12/20-Cty Eslite Home | D68: 5112 | E68: 218208891 | F68: 0
A69: 44166 | B69: 0000040 | C69: Thuế GTGT đầu ra HĐ: 0000040,01/12/20 | D69: 33311 | E69: 21820889 | F69: 0
A70: 44167 | B70: 0000525 | C70: Công Ty Eslite Home Thanh toán tiền HD 525 | D70: 1121IVB | E70: 0 | F70: 0
A71: 44179 | C71: Công Ty Eslite Home thanh toán tiền | D71: 1121IVB | E71: 0 | F71: 0
A72: 44195 | B72: 0000074 | C72: DT bán poly trang trí-HD 74-30/12/20-Cty Eslite Home | D72: 5112 | E72: 292016109 | F72: 0
A73: 44195 | B73: 0000074 | C73: Thuế GTGT đầu ra HĐ: 0000074,30/12/20 | D73: 33311 | E73: 29201611 | F73: 0
E74: =SUM(E68:E73) -> 561247500
A76: Ngày | B76: Số Hđ | D76: DU | E76: Nợ | F76: Có
C77: SỐ DƯ ĐẦU KỲ | D77: 0 | E77: 561247499 | F77: 0
A78: 44197 | C78: Bút toán điều chỉnh chênh lêch thanh toán | D78: 711 | E78: 1 | F78: 0
A79: 44217 | B79: 0000040 | C79: Công Ty Eslite Home thanh toán tiền HD 40 | D79: 1121IVB | E79: 0 | F79: 240029780
A80: 44226 | B80: 0000107 | C80: DT Bán poly-HD 107-30/01/21-Cty ESLITE HOME | D80: 5112 | E80: 62500806 | F80: 0
A81: 44226 | B81: 0000107 | C81: Thuế GTGT đầu ra HĐ: 0000107,30/01/21 | D81: 33311 | E81: 6250081 | F81: 0
A82: 44356 | C82: Công Ty Eslite Home thanh toán tiền hàng | D82: 1121IVB | E82: 0 | F82: 199978000 | I82: =+E72+E73 -> 321217720
A83: 44356 | C83: Phí ngân hàng | D83: 6427 | E83: 0 | F83: 22000 | I83: =+F82+F83 -> 200000000 | J83: =+I82-I83 -> 121217720
A84: 44433 | B84: 0000275 | C84: DT Bán Poly trang trí-HĐ 275-25/08/21-Cty Eslite Home | D84: 5112 | E84: 15755460 | F84: 0
A85: 44433 | B85: 0000275 | C85: Thuế GTGT đầu ra HĐ: 0000275,25/08/21 | D85: 33311 | E85: 1575546 | F85: 0
A86: 44561 | C86: điều chỉnh chênh lệch công nợ | D86: 811 | E86: 0 | F86: 378227
C87: CỘNG PHÁT SINH | E87: 86081894 | F87: 440408007
C88: SỐ DƯ CUỐI KỲ | E88: 206921386 | F88: 0 | J88: =+J83+E80+E81+E84+E85 -> 207299613
A92: 966 | B92: 43620 | C92: Poly trang trí-Công ty TNHH Sản xuất TM B H-966 | D92: 5111 | E92: 104729830 | F92: 0
A93: 966 | B93: 43620 | C93: VAT bán ra - Poly trang trí-Công ty TNHH Sản xuất TM B H-966 | D93: 33311 | E93: 10472983 | F93: 0
A94: 966 | B94: 43754 | C94: Công ty TNHH Sản xuất TM B H thanh toán 50% HD-966 | D94: 1121IVB | E94: 0 | F94: 57601407
C95: Số phát sinh trong kỳ | E95: 115202813 | F95: 57601407
C96: Số dư cuối kỳ | E96: 57601406 | F96: 0
A99: 0 | B99: 43612 | C99: Đặt cọc trước tiền làm viềng | D99: 1121IVB | E99: 0 | F99: 400000000
A100: 12 | B100: 43643 | C100: Poly trang trí-Công Ty TNHH TM Tam Hợp Phát-12 | D100: 1121IVB | E100: 0 | F100: 400000000
A101: 12 | B101: 43645 | C101: Poly trang trí-Công Ty TNHH TM Tam Hợp Phát-12 | D101: 5111 | E101: 765993000 | F101: 0
A102: 12 | B102: 43645 | C102: VAT bán ra - Poly trang trí-Công Ty TNHH TM Tam Hợp Phát-12 | D102: 33311 | E102: 76599300 | F102: 0
A103: 0 | B103: 43668 | C103: Công ty TNHH Tam Hợp Phát đặt cọc tiền hàng | D103: 1121IVB | E103: 0 | F103: 310000000
A104: 65 | B104: 43678 | C104: Poly trang trí-Công Ty TNHH TM Tam Hợp Phát-65 | D104: 5111 | E104: 1539981000 | F104: 0
A105: 65 | B105: 43678 | C105: VAT đầu ra-Poly trang trí-Công Ty TNHH TM Tam Hợp Phát-65 | D105: 33311 | E105: 153998100 | F105: 0
A106: 0 | B106: 43703 | C106: Công ty TNHH Tam Hợp Phát thanh toán tiền hàng | D106: 1121IVB | E106: 0 | F106: 500000000
A107: 104 | B107: 43706 | C107: Poly trang trí-Công Ty TNHH TM Tam Hợp Phát-104 | D107: 5111 | E107: 880942000 | F107: 0
A108: 104 | B108: 43706 | C108: VAT đầu ra-Poly trang trí-Công Ty TNHH TM Tam Hợp Phát-104 | D108: 33311 | E108: 88094200 | F108: 0
A109: 138 | B109: 43733 | C109: Poly trang trí-Công Ty TNHH TM Tam Hợp Phát-138 | D109: 5111 | E109: 588227500 | F109: 0
A110: 138 | B110: 43733 | C110: VAT đầu ra-Poly trang trí-Công Ty TNHH TM Tam Hợp Phát-138 | D110: 33311 | E110: 58822750 | F110: 0
A111: 176 | B111: 43767 | C111: Poly trang trí-Công Ty TNHH TM Tam Hợp Phát-176 | D111: 5111 | E111: 52080500 | F111: 0
A112: 176 | B112: 43767 | C112: VAT đầu ra-Poly trang trí-Công Ty TNHH TM Tam Hợp Phát-176 | D112: 33311 | E112: 5208050 | F112: 0
C113: Số phát sinh trong kỳ | E113: 4209946400 | F113: 1610000000
C114: Số dư cuối kỳ | E114: 2599946400 | F114: 0
C115: SỐ DƯ ĐẦU KỲ | D115: 0 | E115: 2599946400 | F115: 0
A116: 44103 | B116: 0000065 | C116: Cty Tam Hợp Phát thanh toán 1 phần HD 65 | D116: 1121IVB | E116: 0 | F116: 100000000
A117: 44139 | B117: 0000065 | C117: Công ty tam hợp phát thanh toán tiền HD 65 | D117: 1121IVB | E117: 0 | F117: 100000000
A118: 44168 | C118: Công Ty Tam Hợp Phát thanh toán tiền | D118: 1121IVB | E118: 0 | F118: 100000000
C119: CỘNG PHÁT SINH | E119: 0 | F119: 300000000
C120: SỐ DƯ CUỐI KỲ | E120: 2299946400 | F120: 0
...
